package F1;

import java.io.InputStream;
import android.os.BaseBundle;
import com.google.android.gms.internal.ads.OA;
import java.lang.ref.Reference;
import com.google.android.gms.internal.ads.z7;
import com.google.android.gms.internal.ads.Zc;
import com.google.android.gms.ads.nonagon.signalgeneration.zzau;
import com.google.android.gms.internal.ads.fd;
import com.google.android.gms.internal.ads.Eq;
import com.google.android.gms.internal.ads.bf;
import com.google.android.gms.internal.ads.k6;
import com.google.android.gms.internal.ads.af;
import com.google.android.gms.internal.ads.Uo;
import com.google.android.gms.internal.ads.Xo;
import com.google.android.gms.internal.ads.ef;
import com.google.android.gms.internal.ads.pp;
import com.google.android.gms.internal.ads.rp;
import com.google.android.gms.internal.ads.Gg;
import com.google.android.gms.internal.ads.a8;
import com.google.android.gms.internal.ads.wn;
import com.google.android.gms.internal.ads.Dq;
import com.google.android.gms.internal.ads.Aq;
import com.google.android.gms.internal.ads.jp;
import com.google.android.gms.internal.ads.vp;
import com.google.android.gms.internal.ads.Hl;
import com.google.android.gms.internal.ads.gh;
import com.google.android.gms.internal.ads.pm;
import com.google.android.gms.internal.ads.E7;
import com.google.android.gms.internal.ads.wp;
import com.google.android.gms.internal.ads.mf;
import I1.H;
import com.google.android.gms.internal.ads.D7;
import com.google.android.gms.internal.ads.wA;
import java.io.IOException;
import com.google.android.gms.internal.ads.yA;
import java.io.FileInputStream;
import com.google.android.gms.internal.ads.ey;
import com.google.android.gms.internal.ads.oA;
import com.google.android.gms.internal.ads.Qx;
import java.security.GeneralSecurityException;
import com.google.android.gms.internal.ads.ob;
import com.google.android.gms.internal.ads.Fz;
import com.google.android.gms.internal.ads.y7;
import com.google.android.gms.internal.ads.RF;
import com.google.android.gms.internal.ads.sd;
import com.google.android.gms.internal.ads.Z4;
import com.google.android.gms.internal.ads.Sb;
import com.google.android.gms.internal.ads.jf;
import com.google.android.gms.internal.ads.kf;
import com.google.android.gms.internal.ads.Up;
import com.google.android.gms.internal.ads.Bp;
import com.google.android.gms.internal.ads.Ip;
import com.google.android.gms.internal.ads.ye;
import com.google.android.gms.internal.ads.Ci;
import com.google.android.gms.internal.ads.Yj;
import com.google.android.gms.internal.ads.qi;
import com.google.android.gms.internal.ads.in;
import com.google.android.gms.internal.ads.zs;
import com.google.android.gms.internal.ads.at;
import com.google.android.gms.internal.ads.F7;
import com.google.android.gms.internal.ads.rd;
import com.google.android.gms.internal.ads.hc;
import E1.o;
import com.google.android.gms.internal.ads.Fv;
import V2.q;
import n1.i;
import android.os.Handler;
import android.os.Looper;
import android.app.Activity;
import java.util.concurrent.Executor;
import android.graphics.Bitmap;
import com.google.android.gms.internal.ads.m2;
import android.text.SpannableStringBuilder;
import com.google.android.gms.internal.ads.Df;
import java.util.Map$Entry;
import android.text.Layout$Alignment;
import com.google.android.gms.internal.ads.Zf;
import com.google.android.gms.internal.ads.r2;
import android.graphics.BitmapFactory;
import android.util.Base64;
import android.util.Pair;
import java.util.TreeMap;
import Z4.g;
import F4.l;
import android.os.Parcel;
import com.google.android.gms.internal.ads.aB;
import com.google.android.gms.internal.ads.rB;
import com.google.android.gms.internal.ads.IA;
import com.google.android.gms.internal.ads.gs;
import android.os.Parcelable;
import com.google.android.gms.internal.ads.F5;
import com.google.android.gms.internal.ads.fs;
import android.os.DeadObjectException;
import com.google.android.gms.internal.ads.hs;
import android.os.Bundle;
import com.google.android.gms.internal.ads.zr;
import com.google.android.gms.internal.ads.e2;
import com.google.android.gms.internal.ads.nr;
import com.google.android.gms.internal.ads.ls;
import com.google.android.gms.internal.ads.sr;
import com.google.android.gms.internal.ads.rr;
import com.google.android.gms.internal.ads.pr;
import org.json.JSONException;
import com.google.android.gms.internal.ads.f8;
import org.json.JSONObject;
import com.google.android.gms.internal.ads.k4;
import com.google.android.gms.internal.ads.u4;
import android.util.Log;
import android.text.TextUtils;
import com.google.android.gms.internal.ads.Gx;
import java.util.TreeSet;
import java.util.Map;
import java.util.Collections;
import com.google.android.gms.internal.ads.o2;
import android.os.IInterface;
import java.util.List;
import com.google.android.gms.internal.ads.kn;
import com.google.android.gms.ads.internal.client.zzdf;
import J1.j;
import com.google.android.gms.internal.ads.E8;
import com.google.android.gms.internal.ads.C8;
import android.os.RemoteException;
import com.google.android.gms.internal.ads.D8;
import android.os.IBinder;
import y1.s;
import java.util.ArrayList;
import com.google.android.gms.internal.ads.h9;
import android.net.Uri;
import java.util.Iterator;
import F0.v;
import java.util.Set;
import com.google.android.gms.internal.ads.vq;
import java.util.Collection;
import java.util.HashSet;
import java.util.Arrays;
import G0.z;
import F0.w;
import F0.d;
import java.lang.ref.WeakReference;
import android.view.View;
import com.google.android.gms.internal.ads.or;
import com.google.android.gms.internal.ads.Pr;
import com.google.android.gms.internal.ads.MA;
import com.google.android.gms.internal.ads.Ar;
import java.util.HashMap;
import android.webkit.WebView;
import com.google.android.gms.internal.ads.bi;
import java.io.File;
import com.google.android.gms.internal.ads.E5;
import java.util.ArrayDeque;
import java.util.concurrent.ScheduledThreadPoolExecutor;
import android.content.SharedPreferences;
import java.util.concurrent.LinkedBlockingQueue;
import com.google.android.gms.internal.ads.es;
import android.os.HandlerThread;
import com.google.android.gms.internal.ads.Ak;
import com.google.android.gms.internal.ads.Ge;
import Z4.c;
import n5.h;
import Z4.t;
import android.content.Context;
import F4.f;
import h2.b;
import h2.a;
import E1.e;
import com.google.android.gms.internal.ads.Q1;
import com.google.android.gms.internal.ads.Cv;

public final class n implements Cv, Q1, e, a, b, p1.b
{
    public final int C;
    public final Object D = d;
    public Object E = new HashMap();
    public Object F = new ArrayList();
    public Object G;
    public Object H = Gx.b;
    
    public n(final f d, final Context g, final t h) {
        this.C = 4;
        h.e("binaryMessenger", (Object)d);
        this.D = d;
        this.E = new c(new X.a((Object)new Z4.e(d), 1));
        this.G = g;
        this.H = h;
    }
    
    public n(final Context context, final E1.c g, final J1.a h) {
        this.C = 7;
        this.D = new Object();
        this.E = context.getApplicationContext();
        this.H = h;
        this.G = g;
    }
    
    public n(final Context context, final Ge f, final Ge e, final Ak g) {
        this.C = 8;
        Context applicationContext = context;
        if (context.getApplicationContext() != null) {
            applicationContext = context.getApplicationContext();
        }
        this.D = applicationContext;
        this.F = f;
        this.E = e;
        this.H = null;
        this.G = g;
    }
    
    public n(final Context context, final String e, final String f) {
        this.C = 16;
        this.E = e;
        this.F = f;
        final HandlerThread h = new HandlerThread("GassClient");
        ((Thread)(this.H = h)).start();
        final es d = new es(9200000, context, h.getLooper(), (a)this, (b)this);
        this.D = d;
        this.G = new LinkedBlockingQueue();
        ((h2.d)d).d();
    }
    
    public n(final SharedPreferences d, final ScheduledThreadPoolExecutor h) {
        this.C = 2;
        this.G = new ArrayDeque();
        this.D = d;
        this.E = "topic_operation_queue";
        this.F = ",";
        this.H = h;
    }
    
    public n(final E5 d, final File e, final File g, final File f) {
        this.C = 17;
        this.D = d;
        this.E = e;
        this.F = f;
        this.G = g;
    }
    
    public n(final bi d, final WebView e) {
        this.C = 15;
        final HashMap g = new HashMap();
        this.G = g;
        this.H = new Ar();
        if (!MA.x.D) {
            throw new IllegalStateException("Method called before OM SDK activation");
        }
        this.D = d;
        this.E = e;
        final Pr pr = (Pr)this.F;
        Object o;
        if (pr == null) {
            o = null;
        }
        else {
            o = ((Reference)pr).get();
        }
        if (o != e) {
            final Iterator iterator = g.values().iterator();
            while (iterator.hasNext()) {
                ((or)iterator.next()).b((View)e);
            }
            this.F = new WeakReference((Object)e);
        }
        if (!d.a("WEB_MESSAGE_LISTENER")) {
            throw new UnsupportedOperationException("The JavaScriptSessionService cannot be supported in this WebView version.");
        }
        final Uri a = w.a;
        if (((G0.c)z.J).b()) {
            w.f((WebView)this.E).a.removeWebMessageListener("omidJsSessionService");
            w.b((WebView)this.E, "omidJsSessionService", (Set)new HashSet((Collection)Arrays.asList((Object[])new String[] { "*" })), (v)new vq((Object)this, 1));
            return;
        }
        throw z.a();
    }
    
    public n(final h9 d) {
        Object o;
        while (true) {
            this.C = 6;
            this.E = new ArrayList();
            this.G = new s();
            this.H = new ArrayList();
            this.D = d;
            o = null;
        Label_0182:
            while (true) {
                Object o2 = null;
                Label_0147: {
                    IBinder binder = null;
                    Label_0137: {
                        try {
                            final List x = d.x();
                            if (x == null) {
                                break;
                            }
                            final Iterator iterator = x.iterator();
                            if (iterator.hasNext()) {
                                final Object next = iterator.next();
                                if (next instanceof IBinder) {
                                    binder = (IBinder)next;
                                    if (binder != null) {
                                        final IInterface queryLocalInterface = binder.queryLocalInterface("com.google.android.gms.ads.internal.formats.client.INativeAdImage");
                                        if (queryLocalInterface instanceof D8) {
                                            o2 = queryLocalInterface;
                                            break Label_0147;
                                        }
                                        break Label_0137;
                                    }
                                }
                                o2 = null;
                                break Label_0147;
                            }
                            break;
                        }
                        catch (final RemoteException ex) {
                            break Label_0182;
                        }
                    }
                    o2 = new C8(binder);
                }
                if (o2 != null) {
                    ((ArrayList)this.E).add((Object)new E8((D8)o2));
                    continue;
                }
                continue;
            }
            final RemoteException ex;
            j.g("", (Throwable)ex);
            break;
        }
        while (true) {
        Label_0288:
            while (true) {
                b0 zzb = null;
                Label_0253: {
                    try {
                        final List d2 = ((h9)this.D).D();
                        if (d2 == null) {
                            break;
                        }
                        final Iterator iterator2 = d2.iterator();
                        if (!iterator2.hasNext()) {
                            break;
                        }
                        final Object next2 = iterator2.next();
                        if (next2 instanceof IBinder) {
                            zzb = zzdf.zzb((IBinder)next2);
                            break Label_0253;
                        }
                    }
                    catch (final RemoteException ex2) {
                        break Label_0288;
                    }
                    zzb = null;
                }
                if (zzb != null) {
                    ((ArrayList)this.H).add((Object)new c0(zzb));
                    continue;
                }
                continue;
            }
            final RemoteException ex2;
            j.g("", (Throwable)ex2);
            break;
        }
        Object f;
        try {
            final D8 k = ((h9)this.D).k();
            f = o;
            if (k != null) {
                f = new E8(k);
            }
        }
        catch (final RemoteException ex3) {
            j.g("", (Throwable)ex3);
            f = o;
        }
        this.F = f;
        try {
            if (((h9)this.D).e() != null) {
                new kn(((h9)this.D).e());
            }
        }
        catch (final RemoteException ex4) {
            j.g("", (Throwable)ex4);
        }
    }
    
    public n(final o2 d, final HashMap hashMap, final HashMap g, final HashMap h) {
        this.C = 5;
        this.D = d;
        this.G = g;
        this.H = h;
        this.F = Collections.unmodifiableMap((Map)hashMap);
        final TreeSet set = new TreeSet();
        int n = 0;
        d.g(set, false);
        final long[] e = new long[set.size()];
        final Iterator iterator = set.iterator();
        while (iterator.hasNext()) {
            e[n] = (long)iterator.next();
            ++n;
        }
        this.E = e;
    }
    
    public n(final String d, final String e, final String f, final List list) {
        this.C = 1;
        d.getClass();
        this.D = d;
        e.getClass();
        this.E = e;
        this.F = f;
        list.getClass();
        this.G = list;
        final StringBuilder sb = new StringBuilder();
        sb.append(d);
        sb.append("-");
        sb.append(e);
        sb.append("-");
        sb.append(f);
        this.H = sb.toString();
    }
    
    public static n b(final SharedPreferences sharedPreferences, final ScheduledThreadPoolExecutor scheduledThreadPoolExecutor) {
        final n n = new n(sharedPreferences, scheduledThreadPoolExecutor);
        final ArrayDeque arrayDeque;
        monitorenter(arrayDeque = (ArrayDeque)n.G);
        Label_0121: {
            try {
                ((ArrayDeque)n.G).clear();
                final String string = ((SharedPreferences)n.D).getString((String)n.E, "");
                if (TextUtils.isEmpty((CharSequence)string) || !string.contains((CharSequence)n.F)) {
                    break Label_0121;
                }
                final String[] split = string.split((String)n.F, -1);
                if (split.length == 0) {
                    Log.e("FirebaseMessaging", "Corrupted queue. Please check the queue contents and item separator provided");
                }
                break Label_0121;
            }
            finally {
                monitorexit(arrayDeque);
                while (true) {
                    final String[] split;
                    int n2 = 0;
                    Block_7: {
                        while (true) {
                            final int length;
                            iftrue(Label_0165:)(n2 >= length);
                            break Block_7;
                            ++n2;
                            continue;
                            length = split.length;
                            n2 = 0;
                            continue;
                        }
                        monitorexit(arrayDeque);
                        return n;
                    }
                    final String s = split[n2];
                    iftrue(Label_0159:)(TextUtils.isEmpty((CharSequence)s));
                    ((ArrayDeque)n.G).add((Object)s);
                    continue;
                }
                Label_0165: {
                    monitorexit(arrayDeque);
                }
                return n;
            }
        }
    }
    
    public static void e(final Throwable t) {
        final StringBuilder sb = new StringBuilder();
        sb.append(t.getClass().getSimpleName());
        sb.append(", Message: ");
        sb.append(t.getMessage());
        sb.append(", Stacktrace: ");
        sb.append(Log.getStackTraceString(t));
        Log.e("WebChromeClientImpl", sb.toString());
    }
    
    public static u4 k() {
        final k4 y = u4.Y();
        ((OA)y).e();
        u4.G((u4)((OA)y).D, 32768L);
        return (u4)((OA)y).b();
    }
    
    public static JSONObject m(final Context context, final J1.a a) {
        final JSONObject jsonObject = new JSONObject();
        try {
            if (f8.b.p()) {
                jsonObject.put("package_name", (Object)context.getPackageName());
            }
            jsonObject.put("js", (Object)a.C);
            jsonObject.put("mf", f8.c.p());
            jsonObject.put("cl", (Object)"730675337");
            jsonObject.put("rapid_rc", (Object)"dev");
            jsonObject.put("rapid_rollup", (Object)"HEAD");
            jsonObject.put("admob_module_version", 12451000);
            jsonObject.put("dynamite_local_version", 250915000);
            jsonObject.put("dynamite_version", u2.d.d(context, "com.google.android.gms.ads.dynamite", false));
            jsonObject.put("container_version", 12451000);
            return jsonObject;
        }
        catch (final JSONException ex) {
            return jsonObject;
        }
    }
    
    private final void n() {
    }
    
    public static void r(final n n, final String s) {
        final pr d = pr.D;
        final rr d2 = rr.D;
        final sr e = sr.E;
        final or or = new or(ls.a(d, d2, e, e, false), new e2((bi)n.D, (WebView)n.E, (String)null, (String)null, nr.D), s);
        ((HashMap)n.G).put((Object)s, (Object)or);
        final Pr pr = (Pr)n.F;
        View view;
        if (pr == null) {
            view = null;
        }
        else {
            view = (View)((Reference)pr).get();
        }
        or.b(view);
        for (final zr zr : ((Ar)n.H).a) {
            final View view2 = (View)((Reference)zr.a).get();
            if (or.f) {
                continue;
            }
            or.b.a(view2, zr.c);
        }
        or.c();
    }
    
    public static void u(final Context context, final String s) {
        final Bundle bundle = new Bundle();
        ((BaseBundle)bundle).putString("action", "no_ads_fallback");
        ((BaseBundle)bundle).putString("flow", s);
        final p f = p.f;
        final J1.e a = f.a;
        final String c = f.d.C;
        a.getClass();
        J1.e.n(context, c, bundle, (J1.d)new C3.f(a));
    }
    
    public long E(final int n) {
        return ((long[])this.E)[n];
    }
    
    public void Q(final int n) {
        try {
            ((LinkedBlockingQueue)this.G).put((Object)k());
        }
        catch (final InterruptedException ex) {}
    }
    
    public void T() {
        final LinkedBlockingQueue linkedBlockingQueue = (LinkedBlockingQueue)this.G;
        final HandlerThread handlerThread = (HandlerThread)this.H;
        Object o;
        try {
            o = ((h2.d)this.D).m();
        }
        catch (final IllegalStateException | DeadObjectException ex) {
            o = null;
        }
        if (o == null) {
            goto Label_0215;
        }
        try {
            final fs fs = new fs(1, (String)this.E, (String)this.F);
            final Parcel p1 = ((B2.a)o).P1();
            F5.c(p1, (Parcelable)fs);
            final Parcel k4 = ((B2.a)o).K4(p1, 1);
            final gs gs = (gs)F5.a(k4, com.google.android.gms.internal.ads.gs.CREATOR);
            k4.recycle();
            Label_0170: {
                if (gs.D == null) {
                    try {
                        final byte[] e = gs.E;
                        final IA a = IA.a;
                        final rB c = rB.c;
                        gs.D = u4.n0(e, IA.b);
                        gs.E = null;
                        break Label_0170;
                    }
                    catch (final NullPointerException gs) {}
                    catch (final aB ab) {}
                    throw new IllegalStateException((Throwable)gs);
                }
            }
            gs.d();
            linkedBlockingQueue.put((Object)gs.D);
            this.g();
            handlerThread.quit();
        }
        finally {
            try {
                linkedBlockingQueue.put((Object)k());
            }
            catch (final InterruptedException ex2) {}
            finally {
                this.g();
                handlerThread.quit();
            }
        }
    }
    
    public int a() {
        return ((long[])this.E).length;
    }
    
    public l c() {
        if (this.F == null) {
            this.F = new g(this);
        }
        final g g = (g)this.F;
        h.b((Object)g);
        return (l)g;
    }
    
    public void d() {
    }
    
    public void e0(final e2.b b) {
        try {
            ((LinkedBlockingQueue)this.G).put((Object)k());
        }
        catch (final InterruptedException ex) {}
    }
    
    public ArrayList f(final long n) {
        final o2 o2 = (o2)this.D;
        final ArrayList list = new ArrayList();
        o2.h(n, o2.h, list);
        final TreeMap treeMap = new TreeMap();
        o2.j(n, false, o2.h, treeMap);
        final HashMap hashMap = (HashMap)this.G;
        o2.i(n, (Map)this.F, hashMap, o2.h, treeMap);
        final ArrayList list2 = new ArrayList();
        for (int size = list.size(), i = 0; i < size; ++i) {
            final Pair pair = (Pair)list.get(i);
            final String s = (String)((HashMap)this.H).get(pair.second);
            if (s != null) {
                final byte[] decode = Base64.decode(s, 0);
                final Bitmap decodeByteArray = BitmapFactory.decodeByteArray(decode, 0, decode.length);
                final r2 r2 = (r2)hashMap.get(pair.first);
                r2.getClass();
                list2.add((Object)new Zf((CharSequence)null, (Layout$Alignment)null, (Layout$Alignment)null, decodeByteArray, r2.c, 0, r2.e, r2.b, 0, Integer.MIN_VALUE, -3.4028235E38f, r2.f, r2.g, r2.j, 0.0f));
            }
        }
        for (final Map$Entry map$Entry : treeMap.entrySet()) {
            final r2 r3 = (r2)hashMap.get(map$Entry.getKey());
            r3.getClass();
            final Df df = (Df)map$Entry.getValue();
            final CharSequence a = df.a;
            a.getClass();
            final SpannableStringBuilder spannableStringBuilder = (SpannableStringBuilder)a;
            for (final m2 m2 : (m2[])spannableStringBuilder.getSpans(0, spannableStringBuilder.length(), (Class)m2.class)) {
                spannableStringBuilder.replace(spannableStringBuilder.getSpanStart((Object)m2), spannableStringBuilder.getSpanEnd((Object)m2), (CharSequence)"");
            }
            int n2;
            for (int k = 0; k < spannableStringBuilder.length(); k = n2) {
                n2 = k + 1;
                if (spannableStringBuilder.charAt(k) == ' ') {
                    int n3;
                    for (n3 = n2; n3 < spannableStringBuilder.length() && spannableStringBuilder.charAt(n3) == ' '; ++n3) {}
                    final int n4 = n3 - n2;
                    if (n4 > 0) {
                        spannableStringBuilder.delete(k, n4 + k);
                    }
                }
            }
            if (spannableStringBuilder.length() > 0 && spannableStringBuilder.charAt(0) == ' ') {
                spannableStringBuilder.delete(0, 1);
            }
            int n5;
            for (int l = 0; l < spannableStringBuilder.length() - 1; l = n5) {
                n5 = l + 1;
                if (spannableStringBuilder.charAt(l) == '\n' && spannableStringBuilder.charAt(n5) == ' ') {
                    spannableStringBuilder.delete(n5, l + 2);
                }
            }
            if (spannableStringBuilder.length() > 0 && spannableStringBuilder.charAt(spannableStringBuilder.length() - 1) == ' ') {
                spannableStringBuilder.delete(spannableStringBuilder.length() - 1, spannableStringBuilder.length());
            }
            int n7;
            for (int n6 = 0; n6 < spannableStringBuilder.length() - 1; n6 = n7) {
                n7 = n6 + 1;
                if (spannableStringBuilder.charAt(n6) == ' ' && spannableStringBuilder.charAt(n7) == '\n') {
                    spannableStringBuilder.delete(n6, n7);
                }
            }
            if (spannableStringBuilder.length() > 0 && spannableStringBuilder.charAt(spannableStringBuilder.length() - 1) == '\n') {
                spannableStringBuilder.delete(spannableStringBuilder.length() - 1, spannableStringBuilder.length());
            }
            df.e = r3.c;
            df.f = r3.d;
            df.g = r3.e;
            df.h = r3.b;
            df.l = r3.f;
            df.k = r3.i;
            df.j = r3.h;
            df.n = r3.j;
            list2.add((Object)df.a());
        }
        return list2;
    }
    
    public void g() {
        switch (this.C) {
            default: {
                final es es = (es)this.D;
                if (es != null && (((h2.d)es).q() || ((h2.d)es).r())) {
                    ((h2.d)es).f();
                }
            }
            case 10: {}
        }
    }
    
    public Object get() {
        return new s1.a((Executor)((b5.a)this.D).get(), (o1.e)((b5.a)this.E).get(), (t1.c)((w2.e)this.F).get(), (u1.d)((b5.a)this.G).get(), (v1.c)((b5.a)this.H).get());
    }
    
    public void h(final Runnable runnable) {
        final Context context = (Context)this.G;
        if (context instanceof Activity) {
            ((Activity)context).runOnUiThread(runnable);
        }
        else {
            new Handler(Looper.getMainLooper()).post(runnable);
        }
    }
    
    public void i(final k1.a a, final k1.g g) {
        final n1.j j = (n1.j)this.D;
        final String a2 = (String)this.E;
        if (a2 == null) {
            throw new NullPointerException("Null transportName");
        }
        final k1.e e = (k1.e)this.G;
        if (e != null) {
            final k1.c c = (k1.c)this.F;
            final n1.p p2 = (n1.p)this.H;
            final n1.j b = j.b(a.b);
            final Object o = new Object();
            ((n1.h)o).f = new HashMap();
            ((n1.h)o).d = p2.a.i();
            ((n1.h)o).e = p2.b.i();
            ((n1.h)o).a = a2;
            ((n1.h)o).c = new n1.l(c, (byte[])e.apply(a.a));
            ((n1.h)o).b = null;
            final k1.b c2 = a.c;
            if (c2 != null) {
                ((n1.h)o).g = c2.a;
            }
            final i b2 = ((n1.h)o).b();
            final s1.a a3 = (s1.a)p2.c;
            a3.getClass();
            a3.b.execute((Runnable)new L4.c((Object)a3, (Object)b, (Object)g, (Object)b2, 6));
            return;
        }
        throw new NullPointerException("Null transformer");
    }
    
    public q j() {
        final Object d;
        monitorenter(d = this.D);
    Label_0081_Outer:
        while (true) {
            Label_0032: {
                try {
                    if (this.F != null) {
                        monitorexit(d);
                        break Label_0053;
                    }
                    break Label_0032;
                }
                finally {
                    monitorexit(d);
                    return (q)Fv.D;
                    final SharedPreferences sharedPreferences = (SharedPreferences)this.F;
                    long long1 = 0L;
                    iftrue(Label_0070:)(sharedPreferences != null);
                    while (true) {
                        o.B.j.getClass();
                        iftrue(Label_0116:)(System.currentTimeMillis() - long1 >= (long)f8.d.p());
                        return (q)Fv.D;
                        Label_0070: {
                            long1 = sharedPreferences.getLong("js_last_update", 0L);
                        }
                        continue;
                        Label_0116:
                        return (q)F7.D0((q)((E1.c)this.G).a(m((Context)this.E, (J1.a)this.H)), (at)new hc((Object)this, 0), (Executor)rd.g);
                        this.F = ((Context)this.E).getSharedPreferences("google_ads_flags_meta", 0);
                        monitorexit(d);
                        continue Label_0081_Outer;
                        continue;
                    }
                }
            }
            break;
        }
    }
    
    public int l(final int n) {
        return ((int[])this.D)[n];
    }
    
    public void o(final Object p0) {
        // 
        // This method could not be decompiled.
        // 
        // Original Bytecode:
        // 
        //     1: getfield        F1/n.C:I
        //     4: lookupswitch {
        //                3: 1276
        //               11: 994
        //               12: 725
        //               13: 346
        //          default: 48
        //        }
        //    48: aload_0        
        //    49: getfield        F1/n.H:Ljava/lang/Object;
        //    52: checkcast       Lcom/google/android/gms/internal/ads/wp;
        //    55: astore_3       
        //    56: aload_1        
        //    57: checkcast       Lcom/google/android/gms/internal/ads/Xj;
        //    60: astore_1       
        //    61: aload_3        
        //    62: dup            
        //    63: astore          11
        //    65: monitorenter   
        //    66: aload_1        
        //    67: getfield        com/google/android/gms/internal/ads/vg.g:Lcom/google/android/gms/internal/ads/Kh;
        //    70: getfield        com/google/android/gms/internal/ads/Kh.C:Lcom/google/android/gms/internal/ads/kn;
        //    73: astore          4
        //    75: aload_0        
        //    76: getfield        F1/n.H:Ljava/lang/Object;
        //    79: checkcast       Lcom/google/android/gms/internal/ads/wp;
        //    82: getfield        com/google/android/gms/internal/ads/wp.d:Lcom/google/android/gms/internal/ads/tp;
        //    85: astore          5
        //    87: aload           4
        //    89: getfield        com/google/android/gms/internal/ads/kn.D:Ljava/lang/Object;
        //    92: checkcast       Lcom/google/android/gms/internal/ads/Kh;
        //    95: aload           5
        //    97: putfield        com/google/android/gms/internal/ads/Kh.G:Lcom/google/android/gms/internal/ads/tp;
        //   100: aload_0        
        //   101: getfield        F1/n.D:Ljava/lang/Object;
        //   104: checkcast       Lcom/google/android/gms/internal/ads/wn;
        //   107: aload_1        
        //   108: invokeinterface com/google/android/gms/internal/ads/wn.o:(Ljava/lang/Object;)V
        //   113: aload_0        
        //   114: getfield        F1/n.H:Ljava/lang/Object;
        //   117: checkcast       Lcom/google/android/gms/internal/ads/wp;
        //   120: astore          5
        //   122: aload           5
        //   124: getfield        com/google/android/gms/internal/ads/wp.b:Ljava/util/concurrent/Executor;
        //   127: astore          4
        //   129: aload           5
        //   131: getfield        com/google/android/gms/internal/ads/wp.d:Lcom/google/android/gms/internal/ads/tp;
        //   134: astore          5
        //   136: aload           5
        //   138: invokestatic    java/util/Objects.requireNonNull:(Ljava/lang/Object;)Ljava/lang/Object;
        //   141: pop            
        //   142: new             Lcom/google/android/gms/internal/ads/tl;
        //   145: astore          6
        //   147: aload           6
        //   149: aload           5
        //   151: bipush          11
        //   153: invokespecial   com/google/android/gms/internal/ads/tl.<init>:(Ljava/lang/Object;I)V
        //   156: aload           4
        //   158: aload           6
        //   160: invokeinterface java/util/concurrent/Executor.execute:(Ljava/lang/Runnable;)V
        //   165: aload_0        
        //   166: getfield        F1/n.H:Ljava/lang/Object;
        //   169: checkcast       Lcom/google/android/gms/internal/ads/wp;
        //   172: getfield        com/google/android/gms/internal/ads/wp.d:Lcom/google/android/gms/internal/ads/tp;
        //   175: invokevirtual   com/google/android/gms/internal/ads/tp.d:()V
        //   178: getstatic       com/google/android/gms/internal/ads/a8.c:Lcom/google/android/gms/internal/ads/M3;
        //   181: invokevirtual   com/google/android/gms/internal/ads/M3.p:()Ljava/lang/Object;
        //   184: checkcast       Ljava/lang/Boolean;
        //   187: invokevirtual   java/lang/Boolean.booleanValue:()Z
        //   190: ifeq            265
        //   193: aload_0        
        //   194: getfield        F1/n.E:Ljava/lang/Object;
        //   197: checkcast       Lcom/google/android/gms/internal/ads/Dq;
        //   200: astore          4
        //   202: aload           4
        //   204: ifnull          265
        //   207: aload           4
        //   209: aload_1        
        //   210: getfield        com/google/android/gms/internal/ads/vg.a:Lcom/google/android/gms/internal/ads/Ip;
        //   213: getfield        com/google/android/gms/internal/ads/Ip.b:LY0/h;
        //   216: invokevirtual   com/google/android/gms/internal/ads/Dq.g:(LY0/h;)V
        //   219: aload           4
        //   221: aload_1        
        //   222: getfield        com/google/android/gms/internal/ads/vg.f:Lcom/google/android/gms/internal/ads/zzcuj;
        //   225: getfield        com/google/android/gms/internal/ads/zzcuj.C:Ljava/lang/String;
        //   228: invokevirtual   com/google/android/gms/internal/ads/Dq.e:(Ljava/lang/String;)V
        //   231: aload_0        
        //   232: getfield        F1/n.F:Ljava/lang/Object;
        //   235: checkcast       Lcom/google/android/gms/internal/ads/Aq;
        //   238: astore_1       
        //   239: aload_1        
        //   240: iconst_1       
        //   241: invokeinterface com/google/android/gms/internal/ads/Aq.m0:(Z)Lcom/google/android/gms/internal/ads/Aq;
        //   246: pop            
        //   247: aload           4
        //   249: aload_1        
        //   250: invokevirtual   com/google/android/gms/internal/ads/Dq.a:(Lcom/google/android/gms/internal/ads/Aq;)V
        //   253: aload           4
        //   255: invokevirtual   com/google/android/gms/internal/ads/Dq.h:()V
        //   258: goto            337
        //   261: astore_1       
        //   262: goto            341
        //   265: aload_0        
        //   266: getfield        F1/n.H:Ljava/lang/Object;
        //   269: checkcast       Lcom/google/android/gms/internal/ads/wp;
        //   272: getfield        com/google/android/gms/internal/ads/wp.g:Lcom/google/android/gms/internal/ads/Eq;
        //   275: astore          4
        //   277: aload_0        
        //   278: getfield        F1/n.F:Ljava/lang/Object;
        //   281: checkcast       Lcom/google/android/gms/internal/ads/Aq;
        //   284: astore          5
        //   286: aload           5
        //   288: aload_1        
        //   289: getfield        com/google/android/gms/internal/ads/vg.a:Lcom/google/android/gms/internal/ads/Ip;
        //   292: getfield        com/google/android/gms/internal/ads/Ip.b:LY0/h;
        //   295: invokeinterface com/google/android/gms/internal/ads/Aq.q:(LY0/h;)Lcom/google/android/gms/internal/ads/Aq;
        //   300: pop            
        //   301: aload           5
        //   303: aload_1        
        //   304: getfield        com/google/android/gms/internal/ads/vg.f:Lcom/google/android/gms/internal/ads/zzcuj;
        //   307: getfield        com/google/android/gms/internal/ads/zzcuj.C:Ljava/lang/String;
        //   310: invokeinterface com/google/android/gms/internal/ads/Aq.K:(Ljava/lang/String;)Lcom/google/android/gms/internal/ads/Aq;
        //   315: pop            
        //   316: aload           5
        //   318: iconst_1       
        //   319: invokeinterface com/google/android/gms/internal/ads/Aq.m0:(Z)Lcom/google/android/gms/internal/ads/Aq;
        //   324: pop            
        //   325: aload           4
        //   327: aload           5
        //   329: invokeinterface com/google/android/gms/internal/ads/Aq.m:()Lcom/google/android/gms/internal/ads/Cq;
        //   334: invokevirtual   com/google/android/gms/internal/ads/Eq.b:(Lcom/google/android/gms/internal/ads/Cq;)V
        //   337: aload           11
        //   339: monitorexit    
        //   340: return         
        //   341: aload           11
        //   343: monitorexit    
        //   344: aload_1        
        //   345: athrow         
        //   346: aload_1        
        //   347: checkcast       Lcom/google/android/gms/internal/ads/wi;
        //   350: astore_3       
        //   351: aload_0        
        //   352: getfield        F1/n.H:Ljava/lang/Object;
        //   355: checkcast       Lcom/google/android/gms/internal/ads/rp;
        //   358: astore_1       
        //   359: aload_1        
        //   360: dup            
        //   361: astore          12
        //   363: monitorenter   
        //   364: aload_0        
        //   365: getfield        F1/n.H:Ljava/lang/Object;
        //   368: checkcast       Lcom/google/android/gms/internal/ads/rp;
        //   371: aconst_null    
        //   372: putfield        com/google/android/gms/internal/ads/rp.i:Lcom/google/android/gms/internal/ads/tq;
        //   375: getstatic       com/google/android/gms/internal/ads/D7.U7:Lcom/google/android/gms/internal/ads/z7;
        //   378: astore          7
        //   380: getstatic       F1/q.d:LF1/q;
        //   383: astore          6
        //   385: aload           6
        //   387: getfield        F1/q.c:Lcom/google/android/gms/internal/ads/B7;
        //   390: aload           7
        //   392: invokevirtual   com/google/android/gms/internal/ads/B7.a:(Lcom/google/android/gms/internal/ads/z7;)Ljava/lang/Object;
        //   395: checkcast       Ljava/lang/Boolean;
        //   398: invokevirtual   java/lang/Boolean.booleanValue:()Z
        //   401: ifeq            456
        //   404: aload_3        
        //   405: getfield        com/google/android/gms/internal/ads/vg.g:Lcom/google/android/gms/internal/ads/Kh;
        //   408: getfield        com/google/android/gms/internal/ads/Kh.C:Lcom/google/android/gms/internal/ads/kn;
        //   411: astore          8
        //   413: aload_0        
        //   414: getfield        F1/n.H:Ljava/lang/Object;
        //   417: checkcast       Lcom/google/android/gms/internal/ads/rp;
        //   420: astore          5
        //   422: aload           5
        //   424: getfield        com/google/android/gms/internal/ads/rp.d:Lcom/google/android/gms/internal/ads/sn;
        //   427: astore          4
        //   429: aload           8
        //   431: getfield        com/google/android/gms/internal/ads/kn.D:Ljava/lang/Object;
        //   434: checkcast       Lcom/google/android/gms/internal/ads/Kh;
        //   437: astore          8
        //   439: aload           8
        //   441: aload           4
        //   443: putfield        com/google/android/gms/internal/ads/Kh.D:Lcom/google/android/gms/internal/ads/sn;
        //   446: aload           8
        //   448: aload           5
        //   450: getfield        com/google/android/gms/internal/ads/rp.e:Lcom/google/android/gms/internal/ads/tp;
        //   453: putfield        com/google/android/gms/internal/ads/Kh.G:Lcom/google/android/gms/internal/ads/tp;
        //   456: aload_0        
        //   457: getfield        F1/n.D:Ljava/lang/Object;
        //   460: checkcast       Lcom/google/android/gms/internal/ads/wn;
        //   463: aload_3        
        //   464: invokeinterface com/google/android/gms/internal/ads/wn.o:(Ljava/lang/Object;)V
        //   469: aload           6
        //   471: getfield        F1/q.c:Lcom/google/android/gms/internal/ads/B7;
        //   474: aload           7
        //   476: invokevirtual   com/google/android/gms/internal/ads/B7.a:(Lcom/google/android/gms/internal/ads/z7;)Ljava/lang/Object;
        //   479: checkcast       Ljava/lang/Boolean;
        //   482: invokevirtual   java/lang/Boolean.booleanValue:()Z
        //   485: ifeq            561
        //   488: aload_0        
        //   489: getfield        F1/n.H:Ljava/lang/Object;
        //   492: checkcast       Lcom/google/android/gms/internal/ads/rp;
        //   495: getfield        com/google/android/gms/internal/ads/rp.b:Ljava/util/concurrent/Executor;
        //   498: astore          4
        //   500: new             Lcom/google/android/gms/internal/ads/qp;
        //   503: astore          5
        //   505: aload           5
        //   507: aload_0        
        //   508: iconst_0       
        //   509: invokespecial   com/google/android/gms/internal/ads/qp.<init>:(LF1/n;I)V
        //   512: aload           4
        //   514: aload           5
        //   516: invokeinterface java/util/concurrent/Executor.execute:(Ljava/lang/Runnable;)V
        //   521: aload_0        
        //   522: getfield        F1/n.H:Ljava/lang/Object;
        //   525: checkcast       Lcom/google/android/gms/internal/ads/rp;
        //   528: getfield        com/google/android/gms/internal/ads/rp.b:Ljava/util/concurrent/Executor;
        //   531: astore          5
        //   533: new             Lcom/google/android/gms/internal/ads/qp;
        //   536: astore          4
        //   538: aload           4
        //   540: aload_0        
        //   541: iconst_1       
        //   542: invokespecial   com/google/android/gms/internal/ads/qp.<init>:(LF1/n;I)V
        //   545: aload           5
        //   547: aload           4
        //   549: invokeinterface java/util/concurrent/Executor.execute:(Ljava/lang/Runnable;)V
        //   554: goto            561
        //   557: astore_3       
        //   558: goto            720
        //   561: getstatic       com/google/android/gms/internal/ads/a8.c:Lcom/google/android/gms/internal/ads/M3;
        //   564: invokevirtual   com/google/android/gms/internal/ads/M3.p:()Ljava/lang/Object;
        //   567: checkcast       Ljava/lang/Boolean;
        //   570: invokevirtual   java/lang/Boolean.booleanValue:()Z
        //   573: ifeq            644
        //   576: aload_0        
        //   577: getfield        F1/n.E:Ljava/lang/Object;
        //   580: checkcast       Lcom/google/android/gms/internal/ads/Dq;
        //   583: astore          4
        //   585: aload           4
        //   587: ifnull          644
        //   590: aload           4
        //   592: aload_3        
        //   593: getfield        com/google/android/gms/internal/ads/vg.a:Lcom/google/android/gms/internal/ads/Ip;
        //   596: getfield        com/google/android/gms/internal/ads/Ip.b:LY0/h;
        //   599: invokevirtual   com/google/android/gms/internal/ads/Dq.g:(LY0/h;)V
        //   602: aload           4
        //   604: aload_3        
        //   605: getfield        com/google/android/gms/internal/ads/vg.f:Lcom/google/android/gms/internal/ads/zzcuj;
        //   608: getfield        com/google/android/gms/internal/ads/zzcuj.C:Ljava/lang/String;
        //   611: invokevirtual   com/google/android/gms/internal/ads/Dq.e:(Ljava/lang/String;)V
        //   614: aload_0        
        //   615: getfield        F1/n.F:Ljava/lang/Object;
        //   618: checkcast       Lcom/google/android/gms/internal/ads/Aq;
        //   621: astore_3       
        //   622: aload_3        
        //   623: iconst_1       
        //   624: invokeinterface com/google/android/gms/internal/ads/Aq.m0:(Z)Lcom/google/android/gms/internal/ads/Aq;
        //   629: pop            
        //   630: aload           4
        //   632: aload_3        
        //   633: invokevirtual   com/google/android/gms/internal/ads/Dq.a:(Lcom/google/android/gms/internal/ads/Aq;)V
        //   636: aload           4
        //   638: invokevirtual   com/google/android/gms/internal/ads/Dq.h:()V
        //   641: goto            716
        //   644: aload_0        
        //   645: getfield        F1/n.H:Ljava/lang/Object;
        //   648: checkcast       Lcom/google/android/gms/internal/ads/rp;
        //   651: getfield        com/google/android/gms/internal/ads/rp.g:Lcom/google/android/gms/internal/ads/Eq;
        //   654: astore          4
        //   656: aload_0        
        //   657: getfield        F1/n.F:Ljava/lang/Object;
        //   660: checkcast       Lcom/google/android/gms/internal/ads/Aq;
        //   663: astore          5
        //   665: aload           5
        //   667: aload_3        
        //   668: getfield        com/google/android/gms/internal/ads/vg.a:Lcom/google/android/gms/internal/ads/Ip;
        //   671: getfield        com/google/android/gms/internal/ads/Ip.b:LY0/h;
        //   674: invokeinterface com/google/android/gms/internal/ads/Aq.q:(LY0/h;)Lcom/google/android/gms/internal/ads/Aq;
        //   679: pop            
        //   680: aload           5
        //   682: aload_3        
        //   683: getfield        com/google/android/gms/internal/ads/vg.f:Lcom/google/android/gms/internal/ads/zzcuj;
        //   686: getfield        com/google/android/gms/internal/ads/zzcuj.C:Ljava/lang/String;
        //   689: invokeinterface com/google/android/gms/internal/ads/Aq.K:(Ljava/lang/String;)Lcom/google/android/gms/internal/ads/Aq;
        //   694: pop            
        //   695: aload           5
        //   697: iconst_1       
        //   698: invokeinterface com/google/android/gms/internal/ads/Aq.m0:(Z)Lcom/google/android/gms/internal/ads/Aq;
        //   703: pop            
        //   704: aload           4
        //   706: aload           5
        //   708: invokeinterface com/google/android/gms/internal/ads/Aq.m:()Lcom/google/android/gms/internal/ads/Cq;
        //   713: invokevirtual   com/google/android/gms/internal/ads/Eq.b:(Lcom/google/android/gms/internal/ads/Cq;)V
        //   716: aload           12
        //   718: monitorexit    
        //   719: return         
        //   720: aload           12
        //   722: monitorexit    
        //   723: aload_3        
        //   724: athrow         
        //   725: aload_1        
        //   726: checkcast       Lcom/google/android/gms/internal/ads/vg;
        //   729: astore_3       
        //   730: aload_0        
        //   731: getfield        F1/n.H:Ljava/lang/Object;
        //   734: checkcast       Lcom/google/android/gms/internal/ads/Xo;
        //   737: astore_1       
        //   738: aload_1        
        //   739: dup            
        //   740: astore          12
        //   742: monitorenter   
        //   743: aload_0        
        //   744: getfield        F1/n.H:Ljava/lang/Object;
        //   747: checkcast       Lcom/google/android/gms/internal/ads/Xo;
        //   750: aconst_null    
        //   751: putfield        com/google/android/gms/internal/ads/Xo.j:LV2/q;
        //   754: getstatic       com/google/android/gms/internal/ads/D7.T7:Lcom/google/android/gms/internal/ads/z7;
        //   757: astore          4
        //   759: getstatic       F1/q.d:LF1/q;
        //   762: getfield        F1/q.c:Lcom/google/android/gms/internal/ads/B7;
        //   765: aload           4
        //   767: invokevirtual   com/google/android/gms/internal/ads/B7.a:(Lcom/google/android/gms/internal/ads/z7;)Ljava/lang/Object;
        //   770: checkcast       Ljava/lang/Boolean;
        //   773: invokevirtual   java/lang/Boolean.booleanValue:()Z
        //   776: ifeq            813
        //   779: aload_3        
        //   780: getfield        com/google/android/gms/internal/ads/vg.g:Lcom/google/android/gms/internal/ads/Kh;
        //   783: getfield        com/google/android/gms/internal/ads/Kh.C:Lcom/google/android/gms/internal/ads/kn;
        //   786: astore          4
        //   788: aload_0        
        //   789: getfield        F1/n.H:Ljava/lang/Object;
        //   792: checkcast       Lcom/google/android/gms/internal/ads/Xo;
        //   795: getfield        com/google/android/gms/internal/ads/Xo.d:Lcom/google/android/gms/internal/ads/Wo;
        //   798: astore          5
        //   800: aload           4
        //   802: getfield        com/google/android/gms/internal/ads/kn.D:Ljava/lang/Object;
        //   805: checkcast       Lcom/google/android/gms/internal/ads/Kh;
        //   808: aload           5
        //   810: putfield        com/google/android/gms/internal/ads/Kh.F:Lcom/google/android/gms/internal/ads/Wo;
        //   813: aload_0        
        //   814: getfield        F1/n.D:Ljava/lang/Object;
        //   817: checkcast       Lcom/google/android/gms/internal/ads/wn;
        //   820: aload_3        
        //   821: invokeinterface com/google/android/gms/internal/ads/wn.o:(Ljava/lang/Object;)V
        //   826: getstatic       com/google/android/gms/internal/ads/a8.c:Lcom/google/android/gms/internal/ads/M3;
        //   829: invokevirtual   com/google/android/gms/internal/ads/M3.p:()Ljava/lang/Object;
        //   832: checkcast       Ljava/lang/Boolean;
        //   835: invokevirtual   java/lang/Boolean.booleanValue:()Z
        //   838: ifeq            913
        //   841: aload_0        
        //   842: getfield        F1/n.E:Ljava/lang/Object;
        //   845: checkcast       Lcom/google/android/gms/internal/ads/Dq;
        //   848: astore          4
        //   850: aload           4
        //   852: ifnull          913
        //   855: aload           4
        //   857: aload_3        
        //   858: getfield        com/google/android/gms/internal/ads/vg.a:Lcom/google/android/gms/internal/ads/Ip;
        //   861: getfield        com/google/android/gms/internal/ads/Ip.b:LY0/h;
        //   864: invokevirtual   com/google/android/gms/internal/ads/Dq.g:(LY0/h;)V
        //   867: aload           4
        //   869: aload_3        
        //   870: getfield        com/google/android/gms/internal/ads/vg.f:Lcom/google/android/gms/internal/ads/zzcuj;
        //   873: getfield        com/google/android/gms/internal/ads/zzcuj.C:Ljava/lang/String;
        //   876: invokevirtual   com/google/android/gms/internal/ads/Dq.e:(Ljava/lang/String;)V
        //   879: aload_0        
        //   880: getfield        F1/n.F:Ljava/lang/Object;
        //   883: checkcast       Lcom/google/android/gms/internal/ads/Aq;
        //   886: astore_3       
        //   887: aload_3        
        //   888: iconst_1       
        //   889: invokeinterface com/google/android/gms/internal/ads/Aq.m0:(Z)Lcom/google/android/gms/internal/ads/Aq;
        //   894: pop            
        //   895: aload           4
        //   897: aload_3        
        //   898: invokevirtual   com/google/android/gms/internal/ads/Dq.a:(Lcom/google/android/gms/internal/ads/Aq;)V
        //   901: aload           4
        //   903: invokevirtual   com/google/android/gms/internal/ads/Dq.h:()V
        //   906: goto            985
        //   909: astore_3       
        //   910: goto            989
        //   913: aload_0        
        //   914: getfield        F1/n.H:Ljava/lang/Object;
        //   917: checkcast       Lcom/google/android/gms/internal/ads/Xo;
        //   920: getfield        com/google/android/gms/internal/ads/Xo.h:Lcom/google/android/gms/internal/ads/Eq;
        //   923: astore          4
        //   925: aload_0        
        //   926: getfield        F1/n.F:Ljava/lang/Object;
        //   929: checkcast       Lcom/google/android/gms/internal/ads/Aq;
        //   932: astore          5
        //   934: aload           5
        //   936: aload_3        
        //   937: getfield        com/google/android/gms/internal/ads/vg.a:Lcom/google/android/gms/internal/ads/Ip;
        //   940: getfield        com/google/android/gms/internal/ads/Ip.b:LY0/h;
        //   943: invokeinterface com/google/android/gms/internal/ads/Aq.q:(LY0/h;)Lcom/google/android/gms/internal/ads/Aq;
        //   948: pop            
        //   949: aload           5
        //   951: aload_3        
        //   952: getfield        com/google/android/gms/internal/ads/vg.f:Lcom/google/android/gms/internal/ads/zzcuj;
        //   955: getfield        com/google/android/gms/internal/ads/zzcuj.C:Ljava/lang/String;
        //   958: invokeinterface com/google/android/gms/internal/ads/Aq.K:(Ljava/lang/String;)Lcom/google/android/gms/internal/ads/Aq;
        //   963: pop            
        //   964: aload           5
        //   966: iconst_1       
        //   967: invokeinterface com/google/android/gms/internal/ads/Aq.m0:(Z)Lcom/google/android/gms/internal/ads/Aq;
        //   972: pop            
        //   973: aload           4
        //   975: aload           5
        //   977: invokeinterface com/google/android/gms/internal/ads/Aq.m:()Lcom/google/android/gms/internal/ads/Cq;
        //   982: invokevirtual   com/google/android/gms/internal/ads/Eq.b:(Lcom/google/android/gms/internal/ads/Cq;)V
        //   985: aload           12
        //   987: monitorexit    
        //   988: return         
        //   989: aload           12
        //   991: monitorexit    
        //   992: aload_3        
        //   993: athrow         
        //   994: aload_0        
        //   995: getfield        F1/n.H:Ljava/lang/Object;
        //   998: checkcast       Lcom/google/android/gms/internal/ads/k6;
        //  1001: astore_3       
        //  1002: aload_1        
        //  1003: checkcast       Lcom/google/android/gms/internal/ads/vg;
        //  1006: astore_1       
        //  1007: aload_3        
        //  1008: dup            
        //  1009: astore          11
        //  1011: monitorenter   
        //  1012: aload_1        
        //  1013: getfield        com/google/android/gms/internal/ads/vg.g:Lcom/google/android/gms/internal/ads/Kh;
        //  1016: getfield        com/google/android/gms/internal/ads/Kh.C:Lcom/google/android/gms/internal/ads/kn;
        //  1019: astore          5
        //  1021: aload_0        
        //  1022: getfield        F1/n.H:Ljava/lang/Object;
        //  1025: checkcast       Lcom/google/android/gms/internal/ads/k6;
        //  1028: getfield        com/google/android/gms/internal/ads/k6.E:Ljava/lang/Object;
        //  1031: checkcast       Lcom/google/android/gms/internal/ads/Up;
        //  1034: getfield        com/google/android/gms/internal/ads/Up.E:Ljava/lang/Object;
        //  1037: checkcast       Lcom/google/android/gms/internal/ads/sn;
        //  1040: astore          4
        //  1042: aload           5
        //  1044: getfield        com/google/android/gms/internal/ads/kn.D:Ljava/lang/Object;
        //  1047: checkcast       Lcom/google/android/gms/internal/ads/Kh;
        //  1050: aload           4
        //  1052: putfield        com/google/android/gms/internal/ads/Kh.D:Lcom/google/android/gms/internal/ads/sn;
        //  1055: aload_0        
        //  1056: getfield        F1/n.D:Ljava/lang/Object;
        //  1059: checkcast       Lcom/google/android/gms/internal/ads/kn;
        //  1062: aload_1        
        //  1063: invokevirtual   com/google/android/gms/internal/ads/kn.o:(Ljava/lang/Object;)V
        //  1066: aload_0        
        //  1067: getfield        F1/n.H:Ljava/lang/Object;
        //  1070: checkcast       Lcom/google/android/gms/internal/ads/k6;
        //  1073: getfield        com/google/android/gms/internal/ads/k6.D:Ljava/lang/Object;
        //  1076: checkcast       Lcom/google/android/gms/internal/ads/bf;
        //  1079: invokevirtual   com/google/android/gms/internal/ads/bf.a:()Ljava/util/concurrent/Executor;
        //  1082: astore          4
        //  1084: new             Lcom/google/android/gms/internal/ads/Ag;
        //  1087: astore          5
        //  1089: aload           5
        //  1091: aload_0        
        //  1092: iconst_1       
        //  1093: invokespecial   com/google/android/gms/internal/ads/Ag.<init>:(LF1/n;I)V
        //  1096: aload           4
        //  1098: aload           5
        //  1100: invokeinterface java/util/concurrent/Executor.execute:(Ljava/lang/Runnable;)V
        //  1105: getstatic       com/google/android/gms/internal/ads/a8.c:Lcom/google/android/gms/internal/ads/M3;
        //  1108: invokevirtual   com/google/android/gms/internal/ads/M3.p:()Ljava/lang/Object;
        //  1111: checkcast       Ljava/lang/Boolean;
        //  1114: invokevirtual   java/lang/Boolean.booleanValue:()Z
        //  1117: ifeq            1192
        //  1120: aload_0        
        //  1121: getfield        F1/n.E:Ljava/lang/Object;
        //  1124: checkcast       Lcom/google/android/gms/internal/ads/Dq;
        //  1127: astore          4
        //  1129: aload           4
        //  1131: ifnull          1192
        //  1134: aload           4
        //  1136: aload_1        
        //  1137: getfield        com/google/android/gms/internal/ads/vg.a:Lcom/google/android/gms/internal/ads/Ip;
        //  1140: getfield        com/google/android/gms/internal/ads/Ip.b:LY0/h;
        //  1143: invokevirtual   com/google/android/gms/internal/ads/Dq.g:(LY0/h;)V
        //  1146: aload           4
        //  1148: aload_1        
        //  1149: getfield        com/google/android/gms/internal/ads/vg.f:Lcom/google/android/gms/internal/ads/zzcuj;
        //  1152: getfield        com/google/android/gms/internal/ads/zzcuj.C:Ljava/lang/String;
        //  1155: invokevirtual   com/google/android/gms/internal/ads/Dq.e:(Ljava/lang/String;)V
        //  1158: aload_0        
        //  1159: getfield        F1/n.F:Ljava/lang/Object;
        //  1162: checkcast       Lcom/google/android/gms/internal/ads/Aq;
        //  1165: astore_1       
        //  1166: aload_1        
        //  1167: iconst_1       
        //  1168: invokeinterface com/google/android/gms/internal/ads/Aq.m0:(Z)Lcom/google/android/gms/internal/ads/Aq;
        //  1173: pop            
        //  1174: aload           4
        //  1176: aload_1        
        //  1177: invokevirtual   com/google/android/gms/internal/ads/Dq.a:(Lcom/google/android/gms/internal/ads/Aq;)V
        //  1180: aload           4
        //  1182: invokevirtual   com/google/android/gms/internal/ads/Dq.h:()V
        //  1185: goto            1267
        //  1188: astore_1       
        //  1189: goto            1271
        //  1192: aload_0        
        //  1193: getfield        F1/n.H:Ljava/lang/Object;
        //  1196: checkcast       Lcom/google/android/gms/internal/ads/k6;
        //  1199: getfield        com/google/android/gms/internal/ads/k6.F:Ljava/lang/Object;
        //  1202: checkcast       Lcom/google/android/gms/internal/ads/Eq;
        //  1205: astore          4
        //  1207: aload_0        
        //  1208: getfield        F1/n.F:Ljava/lang/Object;
        //  1211: checkcast       Lcom/google/android/gms/internal/ads/Aq;
        //  1214: astore          5
        //  1216: aload           5
        //  1218: aload_1        
        //  1219: getfield        com/google/android/gms/internal/ads/vg.a:Lcom/google/android/gms/internal/ads/Ip;
        //  1222: getfield        com/google/android/gms/internal/ads/Ip.b:LY0/h;
        //  1225: invokeinterface com/google/android/gms/internal/ads/Aq.q:(LY0/h;)Lcom/google/android/gms/internal/ads/Aq;
        //  1230: pop            
        //  1231: aload           5
        //  1233: aload_1        
        //  1234: getfield        com/google/android/gms/internal/ads/vg.f:Lcom/google/android/gms/internal/ads/zzcuj;
        //  1237: getfield        com/google/android/gms/internal/ads/zzcuj.C:Ljava/lang/String;
        //  1240: invokeinterface com/google/android/gms/internal/ads/Aq.K:(Ljava/lang/String;)Lcom/google/android/gms/internal/ads/Aq;
        //  1245: pop            
        //  1246: aload           5
        //  1248: iconst_1       
        //  1249: invokeinterface com/google/android/gms/internal/ads/Aq.m0:(Z)Lcom/google/android/gms/internal/ads/Aq;
        //  1254: pop            
        //  1255: aload           4
        //  1257: aload           5
        //  1259: invokeinterface com/google/android/gms/internal/ads/Aq.m:()Lcom/google/android/gms/internal/ads/Cq;
        //  1264: invokevirtual   com/google/android/gms/internal/ads/Eq.b:(Lcom/google/android/gms/internal/ads/Cq;)V
        //  1267: aload           11
        //  1269: monitorexit    
        //  1270: return         
        //  1271: aload           11
        //  1273: monitorexit    
        //  1274: aload_1        
        //  1275: athrow         
        //  1276: aload_1        
        //  1277: checkcast       LP1/p;
        //  1280: astore          9
        //  1282: aload_0        
        //  1283: getfield        F1/n.D:Ljava/lang/Object;
        //  1286: checkcast       LV2/q;
        //  1289: aload_0        
        //  1290: getfield        F1/n.E:Ljava/lang/Object;
        //  1293: checkcast       Lcom/google/android/gms/internal/ads/fd;
        //  1296: invokestatic    com/google/android/gms/ads/nonagon/signalgeneration/zzau.w5:(LV2/q;Lcom/google/android/gms/internal/ads/fd;)Lcom/google/android/gms/internal/ads/Dq;
        //  1299: astore_3       
        //  1300: aload_0        
        //  1301: getfield        F1/n.H:Ljava/lang/Object;
        //  1304: checkcast       Lcom/google/android/gms/ads/nonagon/signalgeneration/zzau;
        //  1307: astore          8
        //  1309: aload           8
        //  1311: getfield        com/google/android/gms/ads/nonagon/signalgeneration/zzau.d0:Ljava/util/concurrent/atomic/AtomicBoolean;
        //  1314: astore_1       
        //  1315: aload           8
        //  1317: getfield        com/google/android/gms/ads/nonagon/signalgeneration/zzau.S:Ljava/lang/String;
        //  1320: astore          7
        //  1322: aload           8
        //  1324: getfield        com/google/android/gms/ads/nonagon/signalgeneration/zzau.T:Ljava/lang/String;
        //  1327: astore          6
        //  1329: aload_1        
        //  1330: iconst_1       
        //  1331: invokevirtual   java/util/concurrent/atomic/AtomicBoolean.set:(Z)V
        //  1334: getstatic       com/google/android/gms/internal/ads/D7.s7:Lcom/google/android/gms/internal/ads/z7;
        //  1337: astore_1       
        //  1338: getstatic       F1/q.d:LF1/q;
        //  1341: getfield        F1/q.c:Lcom/google/android/gms/internal/ads/B7;
        //  1344: aload_1        
        //  1345: invokevirtual   com/google/android/gms/internal/ads/B7.a:(Lcom/google/android/gms/internal/ads/z7;)Ljava/lang/Object;
        //  1348: checkcast       Ljava/lang/Boolean;
        //  1351: invokevirtual   java/lang/Boolean.booleanValue:()Z
        //  1354: istore_2       
        //  1355: aload_0        
        //  1356: getfield        F1/n.G:Ljava/lang/Object;
        //  1359: checkcast       Lcom/google/android/gms/internal/ads/Aq;
        //  1362: astore          4
        //  1364: aload_0        
        //  1365: getfield        F1/n.F:Ljava/lang/Object;
        //  1368: checkcast       Lcom/google/android/gms/internal/ads/Zc;
        //  1371: astore          5
        //  1373: iload_2        
        //  1374: ifne            1461
        //  1377: aload           5
        //  1379: ifnull          1409
        //  1382: aload           5
        //  1384: ldc_w           "QueryInfo generation has been disabled."
        //  1387: invokeinterface com/google/android/gms/internal/ads/Zc.y:(Ljava/lang/String;)V
        //  1392: goto            1409
        //  1395: astore_1       
        //  1396: ldc_w           "QueryInfo generation has been disabled."
        //  1399: aload_1        
        //  1400: invokevirtual   java/lang/Object.toString:()Ljava/lang/String;
        //  1403: invokevirtual   java/lang/String.concat:(Ljava/lang/String;)Ljava/lang/String;
        //  1406: invokestatic    J1/j.f:(Ljava/lang/String;)V
        //  1409: getstatic       com/google/android/gms/internal/ads/a8.e:Lcom/google/android/gms/internal/ads/M3;
        //  1412: invokevirtual   com/google/android/gms/internal/ads/M3.p:()Ljava/lang/Object;
        //  1415: checkcast       Ljava/lang/Boolean;
        //  1418: invokevirtual   java/lang/Boolean.booleanValue:()Z
        //  1421: ifeq            2022
        //  1424: aload_3        
        //  1425: ifnull          2022
        //  1428: aload           4
        //  1430: ldc_w           "QueryInfo generation has been disabled."
        //  1433: invokeinterface com/google/android/gms/internal/ads/Aq.v:(Ljava/lang/String;)Lcom/google/android/gms/internal/ads/Aq;
        //  1438: pop            
        //  1439: aload           4
        //  1441: iconst_0       
        //  1442: invokeinterface com/google/android/gms/internal/ads/Aq.m0:(Z)Lcom/google/android/gms/internal/ads/Aq;
        //  1447: pop            
        //  1448: aload_3        
        //  1449: aload           4
        //  1451: invokevirtual   com/google/android/gms/internal/ads/Dq.a:(Lcom/google/android/gms/internal/ads/Aq;)V
        //  1454: aload_3        
        //  1455: invokevirtual   com/google/android/gms/internal/ads/Dq.h:()V
        //  1458: goto            2022
        //  1461: aload           9
        //  1463: ifnonnull       1533
        //  1466: aload           5
        //  1468: ifnull          1492
        //  1471: aload           5
        //  1473: aconst_null    
        //  1474: aconst_null    
        //  1475: aconst_null    
        //  1476: invokeinterface com/google/android/gms/internal/ads/Zc.u2:(Ljava/lang/String;Ljava/lang/String;Landroid/os/Bundle;)V
        //  1481: goto            1492
        //  1484: astore_1       
        //  1485: goto            2023
        //  1488: astore_1       
        //  1489: goto            1962
        //  1492: aload           4
        //  1494: iconst_1       
        //  1495: invokeinterface com/google/android/gms/internal/ads/Aq.m0:(Z)Lcom/google/android/gms/internal/ads/Aq;
        //  1500: pop            
        //  1501: getstatic       com/google/android/gms/internal/ads/a8.e:Lcom/google/android/gms/internal/ads/M3;
        //  1504: invokevirtual   com/google/android/gms/internal/ads/M3.p:()Ljava/lang/Object;
        //  1507: checkcast       Ljava/lang/Boolean;
        //  1510: invokevirtual   java/lang/Boolean.booleanValue:()Z
        //  1513: ifeq            2022
        //  1516: aload_3        
        //  1517: ifnull          2022
        //  1520: aload_3        
        //  1521: aload           4
        //  1523: invokevirtual   com/google/android/gms/internal/ads/Dq.a:(Lcom/google/android/gms/internal/ads/Aq;)V
        //  1526: aload_3        
        //  1527: invokevirtual   com/google/android/gms/internal/ads/Dq.h:()V
        //  1530: goto            2022
        //  1533: aload           9
        //  1535: getfield        P1/p.a:Ljava/lang/String;
        //  1538: astore          10
        //  1540: aload           9
        //  1542: getfield        P1/p.c:Ljava/lang/String;
        //  1545: invokestatic    android/text/TextUtils.isEmpty:(Ljava/lang/CharSequence;)Z
        //  1548: ifne            1571
        //  1551: new             Lorg/json/JSONObject;
        //  1554: astore_1       
        //  1555: aload_1        
        //  1556: aload           9
        //  1558: getfield        P1/p.c:Ljava/lang/String;
        //  1561: invokespecial   org/json/JSONObject.<init>:(Ljava/lang/String;)V
        //  1564: goto            1584
        //  1567: astore_1       
        //  1568: goto            1859
        //  1571: new             Lorg/json/JSONObject;
        //  1574: dup            
        //  1575: aload           9
        //  1577: getfield        P1/p.b:Ljava/lang/String;
        //  1580: invokespecial   org/json/JSONObject.<init>:(Ljava/lang/String;)V
        //  1583: astore_1       
        //  1584: aload_1        
        //  1585: ldc_w           "request_id"
        //  1588: ldc_w           ""
        //  1591: invokevirtual   org/json/JSONObject.optString:(Ljava/lang/String;Ljava/lang/String;)Ljava/lang/String;
        //  1594: invokestatic    android/text/TextUtils.isEmpty:(Ljava/lang/CharSequence;)Z
        //  1597: ifeq            1663
        //  1600: ldc_w           "The request ID is empty in request JSON."
        //  1603: invokestatic    J1/j.i:(Ljava/lang/String;)V
        //  1606: aload           5
        //  1608: ifnull          1621
        //  1611: aload           5
        //  1613: ldc_w           "Internal error: request ID is empty in request JSON."
        //  1616: invokeinterface com/google/android/gms/internal/ads/Zc.y:(Ljava/lang/String;)V
        //  1621: aload           4
        //  1623: ldc_w           "Request ID empty"
        //  1626: invokeinterface com/google/android/gms/internal/ads/Aq.v:(Ljava/lang/String;)Lcom/google/android/gms/internal/ads/Aq;
        //  1631: pop            
        //  1632: aload           4
        //  1634: iconst_0       
        //  1635: invokeinterface com/google/android/gms/internal/ads/Aq.m0:(Z)Lcom/google/android/gms/internal/ads/Aq;
        //  1640: pop            
        //  1641: getstatic       com/google/android/gms/internal/ads/a8.e:Lcom/google/android/gms/internal/ads/M3;
        //  1644: invokevirtual   com/google/android/gms/internal/ads/M3.p:()Ljava/lang/Object;
        //  1647: checkcast       Ljava/lang/Boolean;
        //  1650: invokevirtual   java/lang/Boolean.booleanValue:()Z
        //  1653: ifeq            2022
        //  1656: aload_3        
        //  1657: ifnull          2022
        //  1660: goto            1520
        //  1663: aload           9
        //  1665: getfield        P1/p.f:Landroid/os/Bundle;
        //  1668: astore_1       
        //  1669: aload           8
        //  1671: getfield        com/google/android/gms/ads/nonagon/signalgeneration/zzau.R:Z
        //  1674: ifeq            1706
        //  1677: aload_1        
        //  1678: ifnull          1706
        //  1681: aload_1        
        //  1682: aload           6
        //  1684: iconst_m1      
        //  1685: invokevirtual   android/os/BaseBundle.getInt:(Ljava/lang/String;I)I
        //  1688: iconst_m1      
        //  1689: if_icmpne       1706
        //  1692: aload_1        
        //  1693: aload           6
        //  1695: aload           8
        //  1697: getfield        com/google/android/gms/ads/nonagon/signalgeneration/zzau.U:Ljava/util/concurrent/atomic/AtomicInteger;
        //  1700: invokevirtual   java/util/concurrent/atomic/AtomicInteger.get:()I
        //  1703: invokevirtual   android/os/BaseBundle.putInt:(Ljava/lang/String;I)V
        //  1706: aload           8
        //  1708: getfield        com/google/android/gms/ads/nonagon/signalgeneration/zzau.Q:Z
        //  1711: ifeq            1779
        //  1714: aload_1        
        //  1715: ifnull          1779
        //  1718: aload_1        
        //  1719: aload           7
        //  1721: invokevirtual   android/os/BaseBundle.getString:(Ljava/lang/String;)Ljava/lang/String;
        //  1724: invokestatic    android/text/TextUtils.isEmpty:(Ljava/lang/CharSequence;)Z
        //  1727: ifeq            1779
        //  1730: aload           8
        //  1732: getfield        com/google/android/gms/ads/nonagon/signalgeneration/zzau.W:Ljava/lang/String;
        //  1735: invokestatic    android/text/TextUtils.isEmpty:(Ljava/lang/CharSequence;)Z
        //  1738: ifeq            1768
        //  1741: aload           8
        //  1743: getstatic       E1/o.B:LE1/o;
        //  1746: getfield        E1/o.c:LI1/M;
        //  1749: aload           8
        //  1751: getfield        com/google/android/gms/ads/nonagon/signalgeneration/zzau.D:Landroid/content/Context;
        //  1754: aload           8
        //  1756: getfield        com/google/android/gms/ads/nonagon/signalgeneration/zzau.V:LJ1/a;
        //  1759: getfield        J1/a.C:Ljava/lang/String;
        //  1762: invokevirtual   I1/M.x:(Landroid/content/Context;Ljava/lang/String;)Ljava/lang/String;
        //  1765: putfield        com/google/android/gms/ads/nonagon/signalgeneration/zzau.W:Ljava/lang/String;
        //  1768: aload_1        
        //  1769: aload           7
        //  1771: aload           8
        //  1773: getfield        com/google/android/gms/ads/nonagon/signalgeneration/zzau.W:Ljava/lang/String;
        //  1776: invokevirtual   android/os/BaseBundle.putString:(Ljava/lang/String;Ljava/lang/String;)V
        //  1779: aload           5
        //  1781: ifnull          1828
        //  1784: aload           9
        //  1786: getfield        P1/p.c:Ljava/lang/String;
        //  1789: invokestatic    android/text/TextUtils.isEmpty:(Ljava/lang/CharSequence;)Z
        //  1792: ifne            1813
        //  1795: aload           5
        //  1797: aload           10
        //  1799: aload           9
        //  1801: getfield        P1/p.c:Ljava/lang/String;
        //  1804: aload_1        
        //  1805: invokeinterface com/google/android/gms/internal/ads/Zc.u2:(Ljava/lang/String;Ljava/lang/String;Landroid/os/Bundle;)V
        //  1810: goto            1828
        //  1813: aload           5
        //  1815: aload           10
        //  1817: aload           9
        //  1819: getfield        P1/p.b:Ljava/lang/String;
        //  1822: aload_1        
        //  1823: invokeinterface com/google/android/gms/internal/ads/Zc.u2:(Ljava/lang/String;Ljava/lang/String;Landroid/os/Bundle;)V
        //  1828: aload           4
        //  1830: iconst_1       
        //  1831: invokeinterface com/google/android/gms/internal/ads/Aq.m0:(Z)Lcom/google/android/gms/internal/ads/Aq;
        //  1836: pop            
        //  1837: getstatic       com/google/android/gms/internal/ads/a8.e:Lcom/google/android/gms/internal/ads/M3;
        //  1840: invokevirtual   com/google/android/gms/internal/ads/M3.p:()Ljava/lang/Object;
        //  1843: checkcast       Ljava/lang/Boolean;
        //  1846: invokevirtual   java/lang/Boolean.booleanValue:()Z
        //  1849: ifeq            2022
        //  1852: aload_3        
        //  1853: ifnull          2022
        //  1856: goto            1520
        //  1859: ldc_w           "Failed to create JSON object from the request string."
        //  1862: invokestatic    J1/j.i:(Ljava/lang/String;)V
        //  1865: aload           5
        //  1867: ifnull          1909
        //  1870: aload_1        
        //  1871: invokevirtual   java/lang/Object.toString:()Ljava/lang/String;
        //  1874: astore          6
        //  1876: new             Ljava/lang/StringBuilder;
        //  1879: astore          7
        //  1881: aload           7
        //  1883: ldc_w           "Internal error for request JSON: "
        //  1886: invokespecial   java/lang/StringBuilder.<init>:(Ljava/lang/String;)V
        //  1889: aload           7
        //  1891: aload           6
        //  1893: invokevirtual   java/lang/StringBuilder.append:(Ljava/lang/String;)Ljava/lang/StringBuilder;
        //  1896: pop            
        //  1897: aload           5
        //  1899: aload           7
        //  1901: invokevirtual   java/lang/StringBuilder.toString:()Ljava/lang/String;
        //  1904: invokeinterface com/google/android/gms/internal/ads/Zc.y:(Ljava/lang/String;)V
        //  1909: aload           4
        //  1911: aload_1        
        //  1912: invokeinterface com/google/android/gms/internal/ads/Aq.p:(Ljava/lang/Throwable;)Lcom/google/android/gms/internal/ads/Aq;
        //  1917: pop            
        //  1918: aload           4
        //  1920: iconst_0       
        //  1921: invokeinterface com/google/android/gms/internal/ads/Aq.m0:(Z)Lcom/google/android/gms/internal/ads/Aq;
        //  1926: pop            
        //  1927: getstatic       E1/o.B:LE1/o;
        //  1930: getfield        E1/o.g:Lcom/google/android/gms/internal/ads/kd;
        //  1933: ldc_w           "SignalGeneratorImpl.generateSignals.onSuccess"
        //  1936: aload_1        
        //  1937: invokevirtual   com/google/android/gms/internal/ads/kd.h:(Ljava/lang/String;Ljava/lang/Throwable;)V
        //  1940: getstatic       com/google/android/gms/internal/ads/a8.e:Lcom/google/android/gms/internal/ads/M3;
        //  1943: invokevirtual   com/google/android/gms/internal/ads/M3.p:()Ljava/lang/Object;
        //  1946: checkcast       Ljava/lang/Boolean;
        //  1949: invokevirtual   java/lang/Boolean.booleanValue:()Z
        //  1952: ifeq            2022
        //  1955: aload_3        
        //  1956: ifnull          2022
        //  1959: goto            1520
        //  1962: aload           4
        //  1964: aload_1        
        //  1965: invokeinterface com/google/android/gms/internal/ads/Aq.p:(Ljava/lang/Throwable;)Lcom/google/android/gms/internal/ads/Aq;
        //  1970: pop            
        //  1971: aload           4
        //  1973: iconst_0       
        //  1974: invokeinterface com/google/android/gms/internal/ads/Aq.m0:(Z)Lcom/google/android/gms/internal/ads/Aq;
        //  1979: pop            
        //  1980: ldc_w           ""
        //  1983: aload_1        
        //  1984: invokestatic    J1/j.g:(Ljava/lang/String;Ljava/lang/Throwable;)V
        //  1987: getstatic       E1/o.B:LE1/o;
        //  1990: getfield        E1/o.g:Lcom/google/android/gms/internal/ads/kd;
        //  1993: ldc_w           "SignalGeneratorImpl.generateSignals.onSuccess"
        //  1996: aload_1        
        //  1997: invokevirtual   com/google/android/gms/internal/ads/kd.h:(Ljava/lang/String;Ljava/lang/Throwable;)V
        //  2000: getstatic       com/google/android/gms/internal/ads/a8.e:Lcom/google/android/gms/internal/ads/M3;
        //  2003: invokevirtual   com/google/android/gms/internal/ads/M3.p:()Ljava/lang/Object;
        //  2006: checkcast       Ljava/lang/Boolean;
        //  2009: invokevirtual   java/lang/Boolean.booleanValue:()Z
        //  2012: ifeq            2022
        //  2015: aload_3        
        //  2016: ifnull          2022
        //  2019: goto            1520
        //  2022: return         
        //  2023: getstatic       com/google/android/gms/internal/ads/a8.e:Lcom/google/android/gms/internal/ads/M3;
        //  2026: invokevirtual   com/google/android/gms/internal/ads/M3.p:()Ljava/lang/Object;
        //  2029: checkcast       Ljava/lang/Boolean;
        //  2032: invokevirtual   java/lang/Boolean.booleanValue:()Z
        //  2035: ifeq            2052
        //  2038: aload_3        
        //  2039: ifnull          2052
        //  2042: aload_3        
        //  2043: aload           4
        //  2045: invokevirtual   com/google/android/gms/internal/ads/Dq.a:(Lcom/google/android/gms/internal/ads/Aq;)V
        //  2048: aload_3        
        //  2049: invokevirtual   com/google/android/gms/internal/ads/Dq.h:()V
        //  2052: aload_1        
        //  2053: athrow         
        //    Exceptions:
        //  Try           Handler
        //  Start  End    Start  End    Type                        
        //  -----  -----  -----  -----  ----------------------------
        //  66     202    261    346    Any
        //  207    258    261    346    Any
        //  265    337    261    346    Any
        //  337    340    261    346    Any
        //  341    344    261    346    Any
        //  364    456    557    725    Any
        //  456    554    557    725    Any
        //  561    585    557    725    Any
        //  590    641    557    725    Any
        //  644    716    557    725    Any
        //  716    719    557    725    Any
        //  720    723    557    725    Any
        //  743    813    909    994    Any
        //  813    850    909    994    Any
        //  855    906    909    994    Any
        //  913    985    909    994    Any
        //  985    988    909    994    Any
        //  989    992    909    994    Any
        //  1012   1129   1188   1276   Any
        //  1134   1185   1188   1276   Any
        //  1192   1267   1188   1276   Any
        //  1267   1270   1188   1276   Any
        //  1271   1274   1188   1276   Any
        //  1382   1392   1395   1409   Landroid/os/RemoteException;
        //  1471   1481   1488   2022   Landroid/os/RemoteException;
        //  1471   1481   1484   2054   Any
        //  1492   1501   1488   2022   Landroid/os/RemoteException;
        //  1492   1501   1484   2054   Any
        //  1533   1564   1567   1962   Lorg/json/JSONException;
        //  1533   1564   1488   2022   Landroid/os/RemoteException;
        //  1533   1564   1484   2054   Any
        //  1571   1584   1567   1962   Lorg/json/JSONException;
        //  1571   1584   1488   2022   Landroid/os/RemoteException;
        //  1571   1584   1484   2054   Any
        //  1584   1606   1488   2022   Landroid/os/RemoteException;
        //  1584   1606   1484   2054   Any
        //  1611   1621   1488   2022   Landroid/os/RemoteException;
        //  1611   1621   1484   2054   Any
        //  1621   1641   1488   2022   Landroid/os/RemoteException;
        //  1621   1641   1484   2054   Any
        //  1663   1677   1488   2022   Landroid/os/RemoteException;
        //  1663   1677   1484   2054   Any
        //  1681   1706   1488   2022   Landroid/os/RemoteException;
        //  1681   1706   1484   2054   Any
        //  1706   1714   1488   2022   Landroid/os/RemoteException;
        //  1706   1714   1484   2054   Any
        //  1718   1768   1488   2022   Landroid/os/RemoteException;
        //  1718   1768   1484   2054   Any
        //  1768   1779   1488   2022   Landroid/os/RemoteException;
        //  1768   1779   1484   2054   Any
        //  1784   1810   1488   2022   Landroid/os/RemoteException;
        //  1784   1810   1484   2054   Any
        //  1813   1828   1488   2022   Landroid/os/RemoteException;
        //  1813   1828   1484   2054   Any
        //  1828   1837   1488   2022   Landroid/os/RemoteException;
        //  1828   1837   1484   2054   Any
        //  1859   1865   1488   2022   Landroid/os/RemoteException;
        //  1859   1865   1484   2054   Any
        //  1870   1909   1488   2022   Landroid/os/RemoteException;
        //  1870   1909   1484   2054   Any
        //  1909   1940   1488   2022   Landroid/os/RemoteException;
        //  1909   1940   1484   2054   Any
        //  1962   2000   1484   2054   Any
        // 
        // The error that occurred was:
        // 
        // java.lang.IndexOutOfBoundsException: Index 857 out of bounds for length 857
        //     at jdk.internal.util.Preconditions.outOfBounds(Preconditions.java:64)
        //     at jdk.internal.util.Preconditions.outOfBoundsCheckIndex(Preconditions.java:70)
        //     at jdk.internal.util.Preconditions.checkIndex(Preconditions.java:266)
        //     at java.util.Objects.checkIndex(Objects.java:385)
        //     at java.util.ArrayList.get(ArrayList.java:434)
        //     at q5.g.d(r8-map-id-5336d296fbf3284427aba3c9406dc63d81d5d24d9edcf157bc560c004a742559:31)
        //     at q5.g.d(r8-map-id-5336d296fbf3284427aba3c9406dc63d81d5d24d9edcf157bc560c004a742559:714)
        //     at q5.g.b(r8-map-id-5336d296fbf3284427aba3c9406dc63d81d5d24d9edcf157bc560c004a742559:2125)
        //     at u5.m.d(r8-map-id-5336d296fbf3284427aba3c9406dc63d81d5d24d9edcf157bc560c004a742559:21)
        //     at u5.i.g(r8-map-id-5336d296fbf3284427aba3c9406dc63d81d5d24d9edcf157bc560c004a742559:23)
        //     at u5.i.f(r8-map-id-5336d296fbf3284427aba3c9406dc63d81d5d24d9edcf157bc560c004a742559:159)
        //     at u5.i.j(r8-map-id-5336d296fbf3284427aba3c9406dc63d81d5d24d9edcf157bc560c004a742559:619)
        //     at u5.i.k(r8-map-id-5336d296fbf3284427aba3c9406dc63d81d5d24d9edcf157bc560c004a742559:13)
        //     at u5.i.i(r8-map-id-5336d296fbf3284427aba3c9406dc63d81d5d24d9edcf157bc560c004a742559:29)
        //     at s5.b.a(r8-map-id-5336d296fbf3284427aba3c9406dc63d81d5d24d9edcf157bc560c004a742559:90)
        //     at com.thesourceofcode.jadec.decompilers.JavaExtractionWorker.decompileWithProcyon(r8-map-id-5336d296fbf3284427aba3c9406dc63d81d5d24d9edcf157bc560c004a742559:367)
        //     at com.thesourceofcode.jadec.decompilers.JavaExtractionWorker.doWork(r8-map-id-5336d296fbf3284427aba3c9406dc63d81d5d24d9edcf157bc560c004a742559:162)
        //     at com.thesourceofcode.jadec.decompilers.BaseDecompiler.withAttempt(r8-map-id-5336d296fbf3284427aba3c9406dc63d81d5d24d9edcf157bc560c004a742559:3)
        //     at z6.a.run(r8-map-id-5336d296fbf3284427aba3c9406dc63d81d5d24d9edcf157bc560c004a742559:31)
        //     at java.util.concurrent.ThreadPoolExecutor.runWorker(ThreadPoolExecutor.java:1156)
        //     at java.util.concurrent.ThreadPoolExecutor$Worker.run(ThreadPoolExecutor.java:651)
        //     at java.lang.Thread.run(Thread.java:1119)
        // 
        throw new IllegalStateException("An error occurred while decompiling this method.");
    }
    
    public void p(final View view) {
        final zs zs = (zs)((in)this.H).e;
        final Yj yj = new Yj((Ci)new qi(15, (byte)0), (ye)null, 1);
        final Up up = new Up((Ip)this.E, (Bp)this.F, (String)null);
        final kf kf = (kf)zs.D;
        final jf jf = new jf(kf.b, kf.c, up, (Sb)yj);
        final kn d = new kn((Object)jf, 28);
        final Z4 z4 = (Z4)this.G;
        synchronized (z4) {
            z4.D = d;
            monitorexit(z4);
            ((sd)this.D).c((Object)jf.S());
        }
    }
    
    public RF q(final int n) {
        return ((RF[])this.E)[n];
    }
    
    public void s(final Object o, final y7 y7, final Fz fz, final boolean b) {
        if (this.E == null) {
            throw new IllegalStateException("addEntry cannot be called after build");
        }
        if (fz.G() == 3) {
            final int ordinal = ((Enum)fz.B()).ordinal();
            byte[] array = null;
            Label_0100: {
                if (ordinal != 1) {
                    if (ordinal != 2) {
                        if (ordinal == 3) {
                            array = ob.E;
                            break Label_0100;
                        }
                        if (ordinal != 4) {
                            throw new GeneralSecurityException("unknown output prefix type");
                        }
                    }
                    array = Qx.a(fz.y()).b();
                }
                else {
                    array = Qx.b(fz.y()).b();
                }
            }
            final oA a = oA.a(array);
            final ey g = new ey(o, a, fz.y(), y7);
            final HashMap hashMap = (HashMap)this.E;
            final ArrayList list = (ArrayList)this.F;
            final ArrayList list2 = new ArrayList();
            list2.add((Object)g);
            final List list3 = (List)hashMap.put((Object)a, (Object)Collections.unmodifiableList((List)list2));
            if (list3 != null) {
                final ArrayList list4 = new ArrayList();
                list4.addAll((Collection)list3);
                list4.add((Object)g);
                hashMap.put((Object)a, (Object)Collections.unmodifiableList((List)list4));
            }
            list.add((Object)g);
            if (b) {
                if (this.G != null) {
                    throw new IllegalStateException("you cannot set two primary primitives");
                }
                this.G = g;
            }
            return;
        }
        throw new GeneralSecurityException("only ENABLED key is allowed");
    }
    
    public byte[] t() {
        if (this.H != null) {
            goto Label_0212;
        }
        Object o = this.G;
        try {
            final FileInputStream fileInputStream = new FileInputStream((File)o);
            try {
                final wA d = yA.D;
                o = new ArrayList();
                final int n = 256;
                final byte[] array = new byte[n];
                Block_7: {
                    int read;
                    for (int i = 0; i < n; i += read) {
                        read = ((InputStream)fileInputStream).read(array, i, n - i);
                        if (read == -1) {
                            break Block_7;
                        }
                    }
                    goto Label_0101;
                }
            }
            catch (final IOException ex) {}
        }
        catch (final IOException ex2) {}
    }
    
    @Override
    public String toString() {
        switch (this.C) {
            default: {
                return super.toString();
            }
            case 1: {
                final StringBuilder sb = new StringBuilder();
                final StringBuilder sb2 = new StringBuilder("FontRequest {mProviderAuthority: ");
                sb2.append((String)this.D);
                sb2.append(", mProviderPackage: ");
                sb2.append((String)this.E);
                sb2.append(", mQuery: ");
                sb2.append((String)this.F);
                sb2.append(", mCertificates:");
                sb.append(sb2.toString());
                int n = 0;
                while (true) {
                    final List list = (List)this.G;
                    if (n >= list.size()) {
                        break;
                    }
                    sb.append(" [");
                    final List list2 = (List)list.get(n);
                    for (int i = 0; i < list2.size(); ++i) {
                        sb.append(" \"");
                        sb.append(Base64.encodeToString((byte[])list2.get(i), 0));
                        sb.append("\"");
                    }
                    sb.append(" ]");
                    ++n;
                }
                sb.append("}mCertificatesArray: 0");
                return sb.toString();
            }
        }
    }
    
    public void v(final Throwable t) {
        switch (this.C) {
            default: {
                if (F1.q.d.c.a(D7.z5)) {
                    I1.H.n("Rewarded ad failed to load", t);
                }
                final mf mf = (mf)((wp)this.H).e.h();
                p0 p;
                if (mf == null) {
                    p = E7.w(t, (pm)null);
                }
                else {
                    p = E7.w(t, mf.d().l);
                }
                final wp wp;
                monitorenter(wp = (wp)this.H);
            Block_19_Outer:
                while (true) {
                    if (mf != null) {
                        Label_0245: {
                            try {
                                ((gh)mf.a0.d()).H0(p);
                                ((wp)this.H).b.execute((Runnable)new Hl((Object)this, 7, (Object)p));
                                break Label_0245;
                            }
                            finally {
                                monitorexit(wp);
                                ((wp)this.H).d.H0(p);
                                ((wp)this.H).b((jp)this.G).b().d().f.i();
                                break Label_0245;
                                final Eq g;
                                Label_0341: {
                                    g = ((wp)this.H).g;
                                }
                                final Aq aq = (Aq)this.F;
                                aq.g(p);
                                aq.p(t);
                                aq.m0(false);
                                g.b(aq.m());
                                while (true) {
                                    while (true) {
                                        monitorexit(wp);
                                        return;
                                        final Dq dq = (Dq)this.E;
                                        iftrue(Label_0341:)(dq == null);
                                        dq.c(p);
                                        final Aq aq2 = (Aq)this.F;
                                        aq2.p(t);
                                        aq2.m0(false);
                                        dq.a(aq2);
                                        dq.h();
                                        continue Block_19_Outer;
                                    }
                                    y7.B(p.C, t, "RewardedAdLoader.onFailure");
                                    ((wn)this.D).a();
                                    iftrue(Label_0341:)(!(boolean)a8.c.p());
                                    continue;
                                }
                            }
                        }
                    }
                    continue;
                }
            }
            case 13: {
                final z7 z5 = D7.z5;
                final F1.q d = F1.q.d;
                if (d.c.a(z5)) {
                    I1.H.n("Interstitial ad failed to load", t);
                }
                final p0 w = E7.w(t, ((Gg)((kf)this.G).c0.d()).l);
                final rp rp;
                monitorenter(rp = (rp)this.H);
                Label_0615: {
                    try {
                        ((rp)this.H).i = null;
                        ((gh)((kf)this.G).W.d()).H0(w);
                        if (d.c.a(D7.U7)) {
                            ((rp)this.H).b.execute((Runnable)new pp(this, w, 0));
                            ((rp)this.H).b.execute((Runnable)new pp(this, w, 1));
                        }
                        break Label_0615;
                    }
                    finally {
                        monitorexit(rp);
                        while (true) {
                            Dq dq2 = null;
                        Block_25:
                            while (true) {
                                dq2 = (Dq)this.E;
                                iftrue(Label_0717:)(dq2 == null);
                                break Block_25;
                                final Eq g2;
                                Label_0717: {
                                    g2 = ((rp)this.H).g;
                                }
                                final Aq aq3 = (Aq)this.F;
                                aq3.g(w);
                                aq3.p(t);
                                aq3.m0(false);
                                g2.b(aq3.m());
                                monitorexit(rp);
                                return;
                                y7.B(w.C, t, "InterstitialAdLoader.onFailure");
                                ((wn)this.D).a();
                                iftrue(Label_0717:)(!(boolean)a8.c.p());
                                continue;
                            }
                            dq2.c(w);
                            final Aq aq4 = (Aq)this.F;
                            aq4.p(t);
                            aq4.m0(false);
                            dq2.a(aq4);
                            dq2.h();
                            continue;
                        }
                    }
                }
            }
            case 12: {
                final z7 z6 = D7.z5;
                final F1.q d2 = F1.q.d;
                if (d2.c.a(z6)) {
                    I1.H.n("App open ad failed to load", t);
                }
                final ef ef = (ef)((Xo)this.H).e.h();
                p0 p2;
                if (ef == null) {
                    p2 = E7.w(t, (pm)null);
                }
                else {
                    p2 = E7.w(t, ef.d().l);
                }
                final Xo xo;
                monitorenter(xo = (Xo)this.H);
                Label_1021: {
                    try {
                        final Xo xo2 = (Xo)this.H;
                        xo2.j = null;
                        if (ef == null) {
                            break Label_1021;
                        }
                        ((gh)ef.Z.d()).H0(p2);
                        if (d2.c.a(D7.T7)) {
                            ((Xo)this.H).b.execute((Runnable)new Hl((Object)this, 5, (Object)p2));
                        }
                        break Label_1021;
                    }
                    finally {
                        monitorexit(xo);
                        final Eq h;
                        Label_1117: {
                            h = ((Xo)this.H).h;
                        }
                        final Aq aq5 = (Aq)this.F;
                        aq5.g(p2);
                        aq5.p(t);
                        aq5.m0(false);
                        h.b(aq5.m());
                        while (true) {
                            Label_1177: {
                                break Label_1177;
                                while (true) {
                                    final Dq dq3;
                                    dq3.c(p2);
                                    final Aq aq6 = (Aq)this.F;
                                    aq6.p(t);
                                    aq6.m0(false);
                                    dq3.a(aq6);
                                    dq3.h();
                                    break Label_1177;
                                    final Xo xo2;
                                    xo2.d.H0(p2);
                                    ((Xo)this.H).b((jp)this.G).a().d().f.i();
                                    break Label_1021;
                                    dq3 = (Dq)this.E;
                                    iftrue(Label_1117:)(dq3 == null);
                                    continue;
                                }
                            }
                            monitorexit(xo);
                            return;
                            y7.B(p2.C, t, "AppOpenAdLoader.onFailure");
                            ((wn)this.D).a();
                            iftrue(Label_1117:)(!(boolean)a8.c.p());
                            continue;
                        }
                    }
                }
            }
            case 11: {
                if (F1.q.d.c.a(D7.z5)) {
                    I1.H.n("Native ad failed to load", t);
                }
                final af af = (af)this.G;
                final p0 w2 = E7.w(t, ((Gg)af.q0.d()).l);
                ((gh)af.m0.d()).H0(w2);
                final k6 k6 = (k6)this.H;
                ((bf)k6.D).a().execute((Runnable)new Hl((Object)this, 4, (Object)w2));
                y7.B(w2.C, t, "NativeAdLoader.onFailure");
                ((kn)this.D).a();
                final boolean booleanValue = (boolean)a8.c.p();
                final Aq aq7 = (Aq)this.F;
                if (booleanValue) {
                    final Dq dq4 = (Dq)this.E;
                    if (dq4 != null) {
                        dq4.c(w2);
                        aq7.p(t);
                        aq7.m0(false);
                        dq4.a(aq7);
                        dq4.h();
                        return;
                    }
                }
                aq7.g(w2);
                aq7.p(t);
                aq7.m0(false);
                ((Eq)k6.F).b(aq7.m());
                return;
            }
            case 3: {
                final String message = t.getMessage();
                if (F1.q.d.c.a(D7.x7)) {
                    o.B.g.g("SignalGeneratorImpl.generateSignals", t);
                }
                else {
                    o.B.g.h("SignalGeneratorImpl.generateSignals", t);
                }
                final Dq w3 = zzau.w5((q)this.D, (fd)this.E);
                if ((boolean)a8.e.p() && w3 != null) {
                    final Aq aq8 = (Aq)this.G;
                    aq8.p(t);
                    aq8.m0(false);
                    w3.a(aq8);
                    w3.h();
                }
                final Zc zc = (Zc)this.F;
                if (zc != null) {
                    try {
                        String string;
                        if ("Unknown format is no longer supported.".equals((Object)message)) {
                            string = message;
                        }
                        else {
                            final StringBuilder sb = new StringBuilder("Internal error. ");
                            sb.append(message);
                            string = sb.toString();
                        }
                        zc.y(string);
                    }
                    catch (final RemoteException ex) {
                        j.g("", (Throwable)ex);
                    }
                }
            }
        }
    }
}
