package P1;

import com.google.android.gms.internal.ads.pd;
import com.google.android.gms.internal.ads.Np;
import J1.a;
import android.content.Context;
import com.google.android.gms.internal.ads.Iv;
import com.google.android.gms.internal.ads.ar;
import java.util.concurrent.ScheduledExecutorService;
import com.google.android.gms.internal.ads.sa;
import com.google.android.gms.internal.ads.yk;
import com.google.android.gms.internal.ads.Dq;
import com.google.android.gms.internal.ads.rd;
import com.google.android.gms.internal.ads.bf;
import com.google.android.gms.internal.ads.sl;
import com.google.android.gms.internal.ads.xh;
import com.google.android.gms.internal.ads.ii;
import com.google.android.gms.internal.ads.FB;
import com.google.android.gms.internal.ads.Kh;
import com.google.android.gms.internal.ads.vh;
import com.google.android.gms.internal.ads.qh;
import com.google.android.gms.internal.ads.y7;
import com.google.android.gms.internal.ads.Ip;
import C2.z;
import com.google.android.gms.internal.ads.of;
import com.google.android.gms.internal.ads.HC;
import com.google.android.gms.internal.ads.Ig;
import com.google.android.gms.internal.ads.We;
import com.google.android.gms.internal.ads.bh;
import com.google.android.gms.internal.ads.dh;
import com.google.android.gms.internal.ads.Zh;
import com.google.android.gms.internal.ads.Dg;
import com.google.android.gms.internal.ads.KC;
import com.google.android.gms.internal.ads.FC;
import com.google.android.gms.internal.ads.GC;

public final class m implements GC
{
    public final int a;
    public final FC b;
    public final FC c;
    public final FC d;
    public final KC e;
    public final KC f;
    public final KC g;
    public final KC h;
    public final KC i;
    public final KC j;
    
    public m(final Dg e, final Dg f, final FC b, final KC g, final Zh h, final t i, final FC c, final dh j, final FC d) {
        this.a = 1;
        this.e = (KC)e;
        this.f = (KC)f;
        this.b = b;
        this.g = g;
        this.h = (KC)h;
        this.i = (KC)i;
        this.c = c;
        this.j = (KC)j;
        this.d = d;
    }
    
    public m(final FC b, final FC c, final o h, final i i, final FC d, final FC e, final FC f, final FC g, final bh j) {
        this.a = 0;
        this.b = b;
        this.c = c;
        this.h = (KC)h;
        this.i = (KC)i;
        this.d = d;
        this.e = (KC)e;
        this.f = (KC)f;
        this.g = (KC)g;
        this.j = (KC)j;
    }
    
    public m(final FC b, final KC h, final FC c, final FC d, final bh j, final FC e, final FC f, final FC g, final FC i) {
        this.a = 7;
        this.b = b;
        this.h = h;
        this.c = c;
        this.d = d;
        this.j = (KC)j;
        this.e = (KC)e;
        this.f = (KC)f;
        this.g = (KC)g;
        this.i = (KC)i;
    }
    
    public m(final FC b, final We h, final Ig i, final FC c, final FC d, final bh j, final FC e, final FC f, final FC g) {
        this.a = 8;
        this.b = b;
        this.h = (KC)h;
        this.i = (KC)i;
        this.c = c;
        this.d = d;
        this.j = (KC)j;
        this.e = (KC)e;
        this.f = (KC)f;
        this.g = (KC)g;
    }
    
    public m(final FC b, final We g, final We h, final FC c, final FC d, final FC e, final We i, final dh j, final FC f) {
        this.a = 3;
        this.b = b;
        this.g = (KC)g;
        this.h = (KC)h;
        this.c = c;
        this.d = d;
        this.e = (KC)e;
        this.i = (KC)i;
        this.j = (KC)j;
        this.f = (KC)f;
    }
    
    public m(final HC g, final HC h, final HC i, final FC b, final FC c, final FC d, final We j, final FC e, final FC f) {
        this.a = 5;
        this.g = (KC)g;
        this.h = (KC)h;
        this.i = (KC)i;
        this.b = b;
        this.c = c;
        this.d = d;
        this.j = (KC)j;
        this.e = (KC)e;
        this.f = (KC)f;
    }
    
    public m(final HC f, final We g, final We h, final bh j, final GC i, final FC b, final FC c, final FC d, final FC e) {
        this.a = 4;
        this.f = (KC)f;
        this.g = (KC)g;
        this.h = (KC)h;
        this.j = (KC)j;
        this.i = (KC)i;
        this.b = b;
        this.c = c;
        this.d = d;
        this.e = (KC)e;
    }
    
    public m(final We h, final FC b, final FC c, final We i, final of of, final FC d, final FC e, final FC f, final FC g, final FC j) {
        this.a = 2;
        this.h = (KC)h;
        this.b = b;
        this.c = c;
        this.i = (KC)i;
        this.d = d;
        this.e = (KC)e;
        this.f = (KC)f;
        this.g = (KC)g;
        this.j = (KC)j;
    }
    
    public m(final We h, final Ig i, final FC b, final FC c, final FC d, final bh j, final FC e, final FC f, final FC g) {
        this.a = 6;
        this.h = (KC)h;
        this.i = (KC)i;
        this.b = b;
        this.c = c;
        this.d = d;
        this.j = (KC)j;
        this.e = (KC)e;
        this.f = (KC)f;
        this.g = (KC)g;
    }
    
    public z a() {
        final Ip ip = (Ip)((Dg)this.e).b.D;
        y7.H((Object)ip);
        return new z(ip, ((Dg)this.f).a(), (qh)this.b.d(), (vh)this.g.d(), ((Zh)this.h).b.o, ((t)this.i).a(), (Kh)this.c.d(), (xh)new FB(((dh)this.j).b.b()), (ii)this.d.d());
    }
    
    public sl b() {
        final bf bf = (bf)((HC)this.f).a;
        final Context b = ((We)this.g).b();
        final a a = ((We)this.h).a();
        final Np a2 = ((bh)this.j).a();
        final pd a3 = rd.a;
        y7.H((Object)a3);
        return new sl(bf, b, a, a2, (Iv)a3, (String)((KC)this.i).d(), (Dq)this.b.d(), (yk)this.c.d(), new sa(11), (ScheduledExecutorService)this.d.d(), (ar)((FC)this.e).d());
    }
    
    public final Object d() {
        // 
        // This method could not be decompiled.
        // 
        // Original Bytecode:
        // 
        //     1: getfield        P1/m.a:I
        //     4: tableswitch {
        //                0: 835
        //                1: 830
        //                2: 717
        //                3: 571
        //                4: 566
        //                5: 453
        //                6: 318
        //                7: 191
        //          default: 52
        //        }
        //    52: aload_0        
        //    53: getfield        P1/m.b:Lcom/google/android/gms/internal/ads/FC;
        //    56: invokevirtual   com/google/android/gms/internal/ads/FC.d:()Ljava/lang/Object;
        //    59: checkcast       Lcom/google/android/gms/internal/ads/Xm;
        //    62: astore          8
        //    64: aload_0        
        //    65: getfield        P1/m.h:Lcom/google/android/gms/internal/ads/KC;
        //    68: checkcast       Lcom/google/android/gms/internal/ads/We;
        //    71: invokevirtual   com/google/android/gms/internal/ads/We.a:()LJ1/a;
        //    74: astore          10
        //    76: aload_0        
        //    77: getfield        P1/m.i:Lcom/google/android/gms/internal/ads/KC;
        //    80: checkcast       Lcom/google/android/gms/internal/ads/Ig;
        //    83: getfield        com/google/android/gms/internal/ads/Ig.b:Lcom/google/android/gms/internal/ads/FC;
        //    86: invokevirtual   com/google/android/gms/internal/ads/FC.d:()Ljava/lang/Object;
        //    89: checkcast       Lcom/google/android/gms/internal/ads/Hg;
        //    92: getfield        com/google/android/gms/internal/ads/Hg.D:Lcom/google/android/gms/internal/ads/hd;
        //    95: getfield        com/google/android/gms/internal/ads/hd.e:Ljava/lang/String;
        //    98: astore          9
        //   100: aload           9
        //   102: invokestatic    com/google/android/gms/internal/ads/y7.H:(Ljava/lang/Object;)V
        //   105: new             Lcom/google/android/gms/internal/ads/Yq;
        //   108: dup            
        //   109: aload           8
        //   111: aload           10
        //   113: aload           9
        //   115: aload_0        
        //   116: getfield        P1/m.c:Lcom/google/android/gms/internal/ads/FC;
        //   119: invokevirtual   com/google/android/gms/internal/ads/FC.d:()Ljava/lang/Object;
        //   122: checkcast       Ljava/lang/String;
        //   125: aload_0        
        //   126: getfield        P1/m.d:Lcom/google/android/gms/internal/ads/FC;
        //   129: invokevirtual   com/google/android/gms/internal/ads/FC.d:()Ljava/lang/Object;
        //   132: checkcast       Landroid/content/Context;
        //   135: aload_0        
        //   136: getfield        P1/m.j:Lcom/google/android/gms/internal/ads/KC;
        //   139: checkcast       Lcom/google/android/gms/internal/ads/bh;
        //   142: getfield        com/google/android/gms/internal/ads/bh.b:Lcom/google/android/gms/internal/ads/Zg;
        //   145: getfield        com/google/android/gms/internal/ads/Zg.d:Lcom/google/android/gms/internal/ads/Jp;
        //   148: aload_0        
        //   149: getfield        P1/m.e:Lcom/google/android/gms/internal/ads/KC;
        //   152: checkcast       Lcom/google/android/gms/internal/ads/FC;
        //   155: invokevirtual   com/google/android/gms/internal/ads/FC.d:()Ljava/lang/Object;
        //   158: checkcast       Lcom/google/android/gms/internal/ads/Kp;
        //   161: aload_0        
        //   162: getfield        P1/m.f:Lcom/google/android/gms/internal/ads/KC;
        //   165: checkcast       Lcom/google/android/gms/internal/ads/FC;
        //   168: invokevirtual   com/google/android/gms/internal/ads/FC.d:()Ljava/lang/Object;
        //   171: checkcast       Lq2/a;
        //   174: aload_0        
        //   175: getfield        P1/m.g:Lcom/google/android/gms/internal/ads/KC;
        //   178: checkcast       Lcom/google/android/gms/internal/ads/FC;
        //   181: invokevirtual   com/google/android/gms/internal/ads/FC.d:()Ljava/lang/Object;
        //   184: checkcast       Lcom/google/android/gms/internal/ads/V4;
        //   187: invokespecial   com/google/android/gms/internal/ads/Yq.<init>:(Lcom/google/android/gms/internal/ads/Xm;LJ1/a;Ljava/lang/String;Ljava/lang/String;Landroid/content/Context;Lcom/google/android/gms/internal/ads/Jp;Lcom/google/android/gms/internal/ads/Kp;Lq2/a;Lcom/google/android/gms/internal/ads/V4;)V
        //   190: areturn        
        //   191: getstatic       com/google/android/gms/internal/ads/rd.a:Lcom/google/android/gms/internal/ads/pd;
        //   194: astore          8
        //   196: aload           8
        //   198: invokestatic    com/google/android/gms/internal/ads/y7.H:(Ljava/lang/Object;)V
        //   201: new             Lcom/google/android/gms/internal/ads/wo;
        //   204: dup            
        //   205: aload           8
        //   207: aload_0        
        //   208: getfield        P1/m.b:Lcom/google/android/gms/internal/ads/FC;
        //   211: invokevirtual   com/google/android/gms/internal/ads/FC.d:()Ljava/lang/Object;
        //   214: checkcast       Ljava/util/concurrent/ScheduledExecutorService;
        //   217: aload_0        
        //   218: getfield        P1/m.h:Lcom/google/android/gms/internal/ads/KC;
        //   221: invokeinterface com/google/android/gms/internal/ads/KC.d:()Ljava/lang/Object;
        //   226: checkcast       Ljava/lang/String;
        //   229: aload_0        
        //   230: getfield        P1/m.c:Lcom/google/android/gms/internal/ads/FC;
        //   233: invokevirtual   com/google/android/gms/internal/ads/FC.d:()Ljava/lang/Object;
        //   236: checkcast       Lcom/google/android/gms/internal/ads/on;
        //   239: aload_0        
        //   240: getfield        P1/m.d:Lcom/google/android/gms/internal/ads/FC;
        //   243: invokevirtual   com/google/android/gms/internal/ads/FC.d:()Ljava/lang/Object;
        //   246: checkcast       Landroid/content/Context;
        //   249: aload_0        
        //   250: getfield        P1/m.j:Lcom/google/android/gms/internal/ads/KC;
        //   253: checkcast       Lcom/google/android/gms/internal/ads/bh;
        //   256: invokevirtual   com/google/android/gms/internal/ads/bh.a:()Lcom/google/android/gms/internal/ads/Np;
        //   259: aload_0        
        //   260: getfield        P1/m.e:Lcom/google/android/gms/internal/ads/KC;
        //   263: checkcast       Lcom/google/android/gms/internal/ads/FC;
        //   266: invokevirtual   com/google/android/gms/internal/ads/FC.d:()Ljava/lang/Object;
        //   269: checkcast       Lcom/google/android/gms/internal/ads/mn;
        //   272: aload_0        
        //   273: getfield        P1/m.f:Lcom/google/android/gms/internal/ads/KC;
        //   276: checkcast       Lcom/google/android/gms/internal/ads/FC;
        //   279: invokevirtual   com/google/android/gms/internal/ads/FC.d:()Ljava/lang/Object;
        //   282: checkcast       Lcom/google/android/gms/internal/ads/mk;
        //   285: aload_0        
        //   286: getfield        P1/m.g:Lcom/google/android/gms/internal/ads/KC;
        //   289: checkcast       Lcom/google/android/gms/internal/ads/FC;
        //   292: invokevirtual   com/google/android/gms/internal/ads/FC.d:()Ljava/lang/Object;
        //   295: checkcast       Lcom/google/android/gms/internal/ads/Tk;
        //   298: aload_0        
        //   299: getfield        P1/m.i:Lcom/google/android/gms/internal/ads/KC;
        //   302: checkcast       Lcom/google/android/gms/internal/ads/FC;
        //   305: invokevirtual   com/google/android/gms/internal/ads/FC.d:()Ljava/lang/Object;
        //   308: checkcast       Ljava/lang/Integer;
        //   311: invokevirtual   java/lang/Integer.intValue:()I
        //   314: invokespecial   com/google/android/gms/internal/ads/wo.<init>:(Lcom/google/android/gms/internal/ads/pd;Ljava/util/concurrent/ScheduledExecutorService;Ljava/lang/String;Lcom/google/android/gms/internal/ads/on;Landroid/content/Context;Lcom/google/android/gms/internal/ads/Np;Lcom/google/android/gms/internal/ads/mn;Lcom/google/android/gms/internal/ads/mk;Lcom/google/android/gms/internal/ads/Tk;I)V
        //   317: areturn        
        //   318: aload_0        
        //   319: getfield        P1/m.h:Lcom/google/android/gms/internal/ads/KC;
        //   322: checkcast       Lcom/google/android/gms/internal/ads/We;
        //   325: invokevirtual   com/google/android/gms/internal/ads/We.b:()Landroid/content/Context;
        //   328: astore          8
        //   330: aload_0        
        //   331: getfield        P1/m.i:Lcom/google/android/gms/internal/ads/KC;
        //   334: checkcast       Lcom/google/android/gms/internal/ads/Ig;
        //   337: getfield        com/google/android/gms/internal/ads/Ig.b:Lcom/google/android/gms/internal/ads/FC;
        //   340: invokevirtual   com/google/android/gms/internal/ads/FC.d:()Ljava/lang/Object;
        //   343: checkcast       Lcom/google/android/gms/internal/ads/Hg;
        //   346: getfield        com/google/android/gms/internal/ads/Hg.D:Lcom/google/android/gms/internal/ads/hd;
        //   349: getfield        com/google/android/gms/internal/ads/hd.e:Ljava/lang/String;
        //   352: astore          9
        //   354: aload           9
        //   356: invokestatic    com/google/android/gms/internal/ads/y7.H:(Ljava/lang/Object;)V
        //   359: new             Lcom/google/android/gms/internal/ads/Un;
        //   362: dup            
        //   363: aload           8
        //   365: aload           9
        //   367: aload_0        
        //   368: getfield        P1/m.b:Lcom/google/android/gms/internal/ads/FC;
        //   371: invokevirtual   com/google/android/gms/internal/ads/FC.d:()Ljava/lang/Object;
        //   374: checkcast       Ljava/lang/String;
        //   377: aload_0        
        //   378: getfield        P1/m.c:Lcom/google/android/gms/internal/ads/FC;
        //   381: invokevirtual   com/google/android/gms/internal/ads/FC.d:()Ljava/lang/Object;
        //   384: checkcast       Lcom/google/android/gms/internal/ads/Hg;
        //   387: aload_0        
        //   388: getfield        P1/m.d:Lcom/google/android/gms/internal/ads/FC;
        //   391: invokevirtual   com/google/android/gms/internal/ads/FC.d:()Ljava/lang/Object;
        //   394: checkcast       Lcom/google/android/gms/internal/ads/Xp;
        //   397: aload_0        
        //   398: getfield        P1/m.j:Lcom/google/android/gms/internal/ads/KC;
        //   401: checkcast       Lcom/google/android/gms/internal/ads/bh;
        //   404: invokevirtual   com/google/android/gms/internal/ads/bh.a:()Lcom/google/android/gms/internal/ads/Np;
        //   407: aload_0        
        //   408: getfield        P1/m.e:Lcom/google/android/gms/internal/ads/KC;
        //   411: checkcast       Lcom/google/android/gms/internal/ads/FC;
        //   414: invokevirtual   com/google/android/gms/internal/ads/FC.d:()Ljava/lang/Object;
        //   417: checkcast       Lcom/google/android/gms/internal/ads/yk;
        //   420: aload_0        
        //   421: getfield        P1/m.f:Lcom/google/android/gms/internal/ads/KC;
        //   424: checkcast       Lcom/google/android/gms/internal/ads/FC;
        //   427: invokevirtual   com/google/android/gms/internal/ads/FC.d:()Ljava/lang/Object;
        //   430: checkcast       Lcom/google/android/gms/internal/ads/Mg;
        //   433: aload_0        
        //   434: getfield        P1/m.g:Lcom/google/android/gms/internal/ads/KC;
        //   437: checkcast       Lcom/google/android/gms/internal/ads/FC;
        //   440: invokevirtual   com/google/android/gms/internal/ads/FC.d:()Ljava/lang/Object;
        //   443: checkcast       Ljava/lang/Long;
        //   446: invokevirtual   java/lang/Long.longValue:()J
        //   449: invokespecial   com/google/android/gms/internal/ads/Un.<init>:(Landroid/content/Context;Ljava/lang/String;Ljava/lang/String;Lcom/google/android/gms/internal/ads/Hg;Lcom/google/android/gms/internal/ads/Xp;Lcom/google/android/gms/internal/ads/Np;Lcom/google/android/gms/internal/ads/yk;Lcom/google/android/gms/internal/ads/Mg;J)V
        //   452: areturn        
        //   453: new             Lcom/google/android/gms/internal/ads/zzejl;
        //   456: dup            
        //   457: aload_0        
        //   458: getfield        P1/m.g:Lcom/google/android/gms/internal/ads/KC;
        //   461: checkcast       Lcom/google/android/gms/internal/ads/HC;
        //   464: getfield        com/google/android/gms/internal/ads/HC.a:Ljava/lang/Object;
        //   467: checkcast       Landroid/content/Context;
        //   470: aload_0        
        //   471: getfield        P1/m.h:Lcom/google/android/gms/internal/ads/KC;
        //   474: checkcast       Lcom/google/android/gms/internal/ads/HC;
        //   477: getfield        com/google/android/gms/internal/ads/HC.a:Ljava/lang/Object;
        //   480: checkcast       LF1/P0;
        //   483: aload_0        
        //   484: getfield        P1/m.i:Lcom/google/android/gms/internal/ads/KC;
        //   487: checkcast       Lcom/google/android/gms/internal/ads/HC;
        //   490: getfield        com/google/android/gms/internal/ads/HC.a:Ljava/lang/Object;
        //   493: checkcast       Ljava/lang/String;
        //   496: aload_0        
        //   497: getfield        P1/m.b:Lcom/google/android/gms/internal/ads/FC;
        //   500: invokevirtual   com/google/android/gms/internal/ads/FC.d:()Ljava/lang/Object;
        //   503: checkcast       Lcom/google/android/gms/internal/ads/rp;
        //   506: aload_0        
        //   507: getfield        P1/m.c:Lcom/google/android/gms/internal/ads/FC;
        //   510: invokevirtual   com/google/android/gms/internal/ads/FC.d:()Ljava/lang/Object;
        //   513: checkcast       Lcom/google/android/gms/internal/ads/sn;
        //   516: aload_0        
        //   517: getfield        P1/m.d:Lcom/google/android/gms/internal/ads/FC;
        //   520: invokevirtual   com/google/android/gms/internal/ads/FC.d:()Ljava/lang/Object;
        //   523: checkcast       Lcom/google/android/gms/internal/ads/tp;
        //   526: aload_0        
        //   527: getfield        P1/m.j:Lcom/google/android/gms/internal/ads/KC;
        //   530: checkcast       Lcom/google/android/gms/internal/ads/We;
        //   533: invokevirtual   com/google/android/gms/internal/ads/We.a:()LJ1/a;
        //   536: aload_0        
        //   537: getfield        P1/m.e:Lcom/google/android/gms/internal/ads/KC;
        //   540: checkcast       Lcom/google/android/gms/internal/ads/FC;
        //   543: invokevirtual   com/google/android/gms/internal/ads/FC.d:()Ljava/lang/Object;
        //   546: checkcast       Lcom/google/android/gms/internal/ads/V4;
        //   549: aload_0        
        //   550: getfield        P1/m.f:Lcom/google/android/gms/internal/ads/KC;
        //   553: checkcast       Lcom/google/android/gms/internal/ads/FC;
        //   556: invokevirtual   com/google/android/gms/internal/ads/FC.d:()Ljava/lang/Object;
        //   559: checkcast       Lcom/google/android/gms/internal/ads/Ak;
        //   562: invokespecial   com/google/android/gms/internal/ads/zzejl.<init>:(Landroid/content/Context;LF1/P0;Ljava/lang/String;Lcom/google/android/gms/internal/ads/rp;Lcom/google/android/gms/internal/ads/sn;Lcom/google/android/gms/internal/ads/tp;LJ1/a;Lcom/google/android/gms/internal/ads/V4;Lcom/google/android/gms/internal/ads/Ak;)V
        //   565: areturn        
        //   566: aload_0        
        //   567: invokevirtual   P1/m.b:()Lcom/google/android/gms/internal/ads/sl;
        //   570: areturn        
        //   571: aload_0        
        //   572: getfield        P1/m.b:Lcom/google/android/gms/internal/ads/FC;
        //   575: invokevirtual   com/google/android/gms/internal/ads/FC.d:()Ljava/lang/Object;
        //   578: checkcast       Ljava/util/concurrent/Executor;
        //   581: astore          10
        //   583: aload_0        
        //   584: getfield        P1/m.g:Lcom/google/android/gms/internal/ads/KC;
        //   587: checkcast       Lcom/google/android/gms/internal/ads/We;
        //   590: invokevirtual   com/google/android/gms/internal/ads/We.b:()Landroid/content/Context;
        //   593: astore          11
        //   595: aload_0        
        //   596: getfield        P1/m.h:Lcom/google/android/gms/internal/ads/KC;
        //   599: checkcast       Lcom/google/android/gms/internal/ads/We;
        //   602: getfield        com/google/android/gms/internal/ads/We.b:Lcom/google/android/gms/internal/ads/Te;
        //   605: getfield        com/google/android/gms/internal/ads/Te.d:Ljava/lang/ref/WeakReference;
        //   608: astore          8
        //   610: aload           8
        //   612: invokestatic    com/google/android/gms/internal/ads/y7.H:(Ljava/lang/Object;)V
        //   615: getstatic       com/google/android/gms/internal/ads/rd.a:Lcom/google/android/gms/internal/ads/pd;
        //   618: astore          9
        //   620: aload           9
        //   622: invokestatic    com/google/android/gms/internal/ads/y7.H:(Ljava/lang/Object;)V
        //   625: new             Lcom/google/android/gms/internal/ads/Sk;
        //   628: dup            
        //   629: aload           10
        //   631: aload           11
        //   633: aload           8
        //   635: aload           9
        //   637: aload_0        
        //   638: getfield        P1/m.c:Lcom/google/android/gms/internal/ads/FC;
        //   641: invokevirtual   com/google/android/gms/internal/ads/FC.d:()Ljava/lang/Object;
        //   644: checkcast       Lcom/google/android/gms/internal/ads/mk;
        //   647: aload_0        
        //   648: getfield        P1/m.d:Lcom/google/android/gms/internal/ads/FC;
        //   651: invokevirtual   com/google/android/gms/internal/ads/FC.d:()Ljava/lang/Object;
        //   654: checkcast       Ljava/util/concurrent/ScheduledExecutorService;
        //   657: aload_0        
        //   658: getfield        P1/m.e:Lcom/google/android/gms/internal/ads/KC;
        //   661: checkcast       Lcom/google/android/gms/internal/ads/FC;
        //   664: invokevirtual   com/google/android/gms/internal/ads/FC.d:()Ljava/lang/Object;
        //   667: checkcast       Lcom/google/android/gms/internal/ads/Fk;
        //   670: aload_0        
        //   671: getfield        P1/m.i:Lcom/google/android/gms/internal/ads/KC;
        //   674: checkcast       Lcom/google/android/gms/internal/ads/We;
        //   677: invokevirtual   com/google/android/gms/internal/ads/We.a:()LJ1/a;
        //   680: new             Lcom/google/android/gms/internal/ads/FB;
        //   683: dup            
        //   684: aload_0        
        //   685: getfield        P1/m.j:Lcom/google/android/gms/internal/ads/KC;
        //   688: checkcast       Lcom/google/android/gms/internal/ads/dh;
        //   691: getfield        com/google/android/gms/internal/ads/dh.b:Lcom/google/android/gms/internal/ads/LC;
        //   694: invokevirtual   com/google/android/gms/internal/ads/LC.b:()Ljava/util/Set;
        //   697: invokespecial   com/google/android/gms/internal/ads/FB.<init>:(Ljava/util/Set;)V
        //   700: aload_0        
        //   701: getfield        P1/m.f:Lcom/google/android/gms/internal/ads/KC;
        //   704: checkcast       Lcom/google/android/gms/internal/ads/FC;
        //   707: invokevirtual   com/google/android/gms/internal/ads/FC.d:()Ljava/lang/Object;
        //   710: checkcast       Lcom/google/android/gms/internal/ads/Eq;
        //   713: invokespecial   com/google/android/gms/internal/ads/Sk.<init>:(Ljava/util/concurrent/Executor;Landroid/content/Context;Ljava/lang/ref/WeakReference;Lcom/google/android/gms/internal/ads/Iv;Lcom/google/android/gms/internal/ads/mk;Ljava/util/concurrent/ScheduledExecutorService;Lcom/google/android/gms/internal/ads/Fk;LJ1/a;Lcom/google/android/gms/internal/ads/ci;Lcom/google/android/gms/internal/ads/Eq;)V
        //   716: areturn        
        //   717: new             Lcom/google/android/gms/internal/ads/Pj;
        //   720: dup            
        //   721: aload_0        
        //   722: getfield        P1/m.h:Lcom/google/android/gms/internal/ads/KC;
        //   725: checkcast       Lcom/google/android/gms/internal/ads/We;
        //   728: invokevirtual   com/google/android/gms/internal/ads/We.b:()Landroid/content/Context;
        //   731: aload_0        
        //   732: getfield        P1/m.b:Lcom/google/android/gms/internal/ads/FC;
        //   735: invokevirtual   com/google/android/gms/internal/ads/FC.d:()Ljava/lang/Object;
        //   738: checkcast       Ljava/util/concurrent/Executor;
        //   741: aload_0        
        //   742: getfield        P1/m.c:Lcom/google/android/gms/internal/ads/FC;
        //   745: invokevirtual   com/google/android/gms/internal/ads/FC.d:()Ljava/lang/Object;
        //   748: checkcast       Lcom/google/android/gms/internal/ads/V4;
        //   751: aload_0        
        //   752: getfield        P1/m.i:Lcom/google/android/gms/internal/ads/KC;
        //   755: checkcast       Lcom/google/android/gms/internal/ads/We;
        //   758: invokevirtual   com/google/android/gms/internal/ads/We.a:()LJ1/a;
        //   761: invokestatic    com/google/android/gms/internal/ads/of.b:()Lcom/google/android/gms/internal/measurement/K1;
        //   764: aload_0        
        //   765: getfield        P1/m.d:Lcom/google/android/gms/internal/ads/FC;
        //   768: invokevirtual   com/google/android/gms/internal/ads/FC.d:()Ljava/lang/Object;
        //   771: checkcast       Lcom/google/android/gms/internal/ads/Yl;
        //   774: aload_0        
        //   775: getfield        P1/m.e:Lcom/google/android/gms/internal/ads/KC;
        //   778: checkcast       Lcom/google/android/gms/internal/ads/FC;
        //   781: invokevirtual   com/google/android/gms/internal/ads/FC.d:()Ljava/lang/Object;
        //   784: checkcast       Lcom/google/android/gms/internal/ads/ar;
        //   787: aload_0        
        //   788: getfield        P1/m.f:Lcom/google/android/gms/internal/ads/KC;
        //   791: checkcast       Lcom/google/android/gms/internal/ads/FC;
        //   794: invokevirtual   com/google/android/gms/internal/ads/FC.d:()Ljava/lang/Object;
        //   797: checkcast       Lcom/google/android/gms/internal/ads/Ak;
        //   800: aload_0        
        //   801: getfield        P1/m.g:Lcom/google/android/gms/internal/ads/KC;
        //   804: checkcast       Lcom/google/android/gms/internal/ads/FC;
        //   807: invokevirtual   com/google/android/gms/internal/ads/FC.d:()Ljava/lang/Object;
        //   810: checkcast       Lcom/google/android/gms/internal/ads/zzeaq;
        //   813: aload_0        
        //   814: getfield        P1/m.j:Lcom/google/android/gms/internal/ads/KC;
        //   817: checkcast       Lcom/google/android/gms/internal/ads/FC;
        //   820: invokevirtual   com/google/android/gms/internal/ads/FC.d:()Ljava/lang/Object;
        //   823: checkcast       Lcom/google/android/gms/internal/ads/Op;
        //   826: invokespecial   com/google/android/gms/internal/ads/Pj.<init>:(Landroid/content/Context;Ljava/util/concurrent/Executor;Lcom/google/android/gms/internal/ads/V4;LJ1/a;Lcom/google/android/gms/internal/measurement/K1;Lcom/google/android/gms/internal/ads/Yl;Lcom/google/android/gms/internal/ads/ar;Lcom/google/android/gms/internal/ads/Ak;Lcom/google/android/gms/internal/ads/zzeaq;Lcom/google/android/gms/internal/ads/Op;)V
        //   829: areturn        
        //   830: aload_0        
        //   831: invokevirtual   P1/m.a:()LC2/z;
        //   834: areturn        
        //   835: aload_0        
        //   836: getfield        P1/m.b:Lcom/google/android/gms/internal/ads/FC;
        //   839: invokevirtual   com/google/android/gms/internal/ads/FC.d:()Ljava/lang/Object;
        //   842: checkcast       Lcom/google/android/gms/ads/nonagon/signalgeneration/zzau;
        //   845: astore          16
        //   847: aload_0        
        //   848: getfield        P1/m.c:Lcom/google/android/gms/internal/ads/FC;
        //   851: invokevirtual   com/google/android/gms/internal/ads/FC.d:()Ljava/lang/Object;
        //   854: checkcast       Lcom/google/android/gms/internal/ads/xq;
        //   857: astore          13
        //   859: aload_0        
        //   860: getfield        P1/m.h:Lcom/google/android/gms/internal/ads/KC;
        //   863: checkcast       LP1/o;
        //   866: astore          8
        //   868: getstatic       com/google/android/gms/internal/ads/rd.a:Lcom/google/android/gms/internal/ads/pd;
        //   871: astore          9
        //   873: aload           9
        //   875: invokestatic    com/google/android/gms/internal/ads/y7.H:(Ljava/lang/Object;)V
        //   878: new             LP1/n;
        //   881: dup            
        //   882: aload           9
        //   884: aload           8
        //   886: getfield        P1/o.b:Lcom/google/android/gms/internal/ads/KC;
        //   889: checkcast       Lcom/google/android/gms/internal/ads/Pc;
        //   892: invokevirtual   com/google/android/gms/internal/ads/Pc.a:()LF1/n;
        //   895: invokespecial   P1/n.<init>:(Lcom/google/android/gms/internal/ads/Iv;LF1/n;)V
        //   898: astore          8
        //   900: aload_0        
        //   901: getfield        P1/m.i:Lcom/google/android/gms/internal/ads/KC;
        //   904: checkcast       LP1/i;
        //   907: invokevirtual   P1/i.a:()Lcom/google/android/gms/internal/ads/Xg;
        //   910: astore          14
        //   912: aload_0        
        //   913: getfield        P1/m.d:Lcom/google/android/gms/internal/ads/FC;
        //   916: invokevirtual   com/google/android/gms/internal/ads/FC.d:()Ljava/lang/Object;
        //   919: checkcast       Lcom/google/android/gms/internal/ads/ui;
        //   922: astore          12
        //   924: aload_0        
        //   925: getfield        P1/m.e:Lcom/google/android/gms/internal/ads/KC;
        //   928: checkcast       Lcom/google/android/gms/internal/ads/FC;
        //   931: invokevirtual   com/google/android/gms/internal/ads/FC.d:()Ljava/lang/Object;
        //   934: checkcast       LP1/j;
        //   937: astore          17
        //   939: aload_0        
        //   940: getfield        P1/m.f:Lcom/google/android/gms/internal/ads/KC;
        //   943: checkcast       Lcom/google/android/gms/internal/ads/FC;
        //   946: invokevirtual   com/google/android/gms/internal/ads/FC.d:()Ljava/lang/Object;
        //   949: checkcast       Lcom/google/android/gms/internal/ads/fd;
        //   952: astore          18
        //   954: aload_0        
        //   955: getfield        P1/m.g:Lcom/google/android/gms/internal/ads/KC;
        //   958: checkcast       Lcom/google/android/gms/internal/ads/FC;
        //   961: invokevirtual   com/google/android/gms/internal/ads/FC.d:()Ljava/lang/Object;
        //   964: checkcast       Ljava/lang/Integer;
        //   967: invokevirtual   java/lang/Integer.intValue:()I
        //   970: istore_1       
        //   971: aload_0        
        //   972: getfield        P1/m.j:Lcom/google/android/gms/internal/ads/KC;
        //   975: checkcast       Lcom/google/android/gms/internal/ads/bh;
        //   978: invokevirtual   com/google/android/gms/internal/ads/bh.a:()Lcom/google/android/gms/internal/ads/Np;
        //   981: getfield        com/google/android/gms/internal/ads/Np.s:Landroid/os/Bundle;
        //   984: astore          15
        //   986: aconst_null    
        //   987: astore          10
        //   989: aconst_null    
        //   990: astore          11
        //   992: iload_1        
        //   993: iconst_1       
        //   994: if_icmpne       2398
        //   997: aload           18
        //   999: ifnonnull       1013
        //  1002: aload           8
        //  1004: astore          9
        //  1006: aload           10
        //  1008: astore          8
        //  1010: goto            2406
        //  1013: getstatic       E1/o.B:LE1/o;
        //  1016: astore          9
        //  1018: aload           9
        //  1020: getfield        E1/o.j:Lq2/a;
        //  1023: invokevirtual   java/lang/Object.getClass:()Ljava/lang/Class;
        //  1026: pop            
        //  1027: aload           15
        //  1029: ldc_w           "read-from-disk-start"
        //  1032: invokestatic    java/lang/System.currentTimeMillis:()J
        //  1035: invokevirtual   android/os/BaseBundle.putLong:(Ljava/lang/String;J)V
        //  1038: aload           17
        //  1040: invokevirtual   java/lang/Object.getClass:()Ljava/lang/Class;
        //  1043: pop            
        //  1044: bipush          30
        //  1046: aload           15
        //  1048: invokestatic    P1/j.c:(ILandroid/os/Bundle;)V
        //  1051: aload           9
        //  1053: getfield        E1/o.g:Lcom/google/android/gms/internal/ads/kd;
        //  1056: invokevirtual   com/google/android/gms/internal/ads/kd.d:()LI1/J;
        //  1059: invokevirtual   I1/J.k:()Z
        //  1062: ifeq            1083
        //  1065: aload           17
        //  1067: getfield        P1/j.b:LP1/u;
        //  1070: invokevirtual   P1/u.c:()V
        //  1073: bipush          7
        //  1075: aload           15
        //  1077: invokestatic    P1/j.d:(ILandroid/os/Bundle;)V
        //  1080: goto            1106
        //  1083: aload           17
        //  1085: getfield        P1/j.e:Landroid/content/pm/PackageInfo;
        //  1088: ifnonnull       1117
        //  1091: aload           17
        //  1093: getfield        P1/j.b:LP1/u;
        //  1096: invokevirtual   P1/u.c:()V
        //  1099: bipush          10
        //  1101: aload           15
        //  1103: invokestatic    P1/j.d:(ILandroid/os/Bundle;)V
        //  1106: aload           8
        //  1108: astore          9
        //  1110: aload           11
        //  1112: astore          8
        //  1114: goto            2349
        //  1117: aload           17
        //  1119: getfield        P1/j.b:LP1/u;
        //  1122: astore          9
        //  1124: aload           17
        //  1126: getfield        P1/j.a:Landroid/content/Context;
        //  1129: astore          11
        //  1131: aload           9
        //  1133: invokevirtual   P1/u.e:()V
        //  1136: aload           9
        //  1138: getfield        P1/u.d:Ljava/lang/Object;
        //  1141: astore          19
        //  1143: aload           19
        //  1145: dup            
        //  1146: astore          25
        //  1148: monitorenter   
        //  1149: aload           9
        //  1151: getfield        P1/u.a:Landroid/content/SharedPreferences;
        //  1154: ldc_w           "pn"
        //  1157: aconst_null    
        //  1158: invokeinterface android/content/SharedPreferences.getString:(Ljava/lang/String;Ljava/lang/String;)Ljava/lang/String;
        //  1163: astore          10
        //  1165: aload           25
        //  1167: monitorexit    
        //  1168: aload           9
        //  1170: invokevirtual   P1/u.e:()V
        //  1173: aload           9
        //  1175: getfield        P1/u.d:Ljava/lang/Object;
        //  1178: astore          19
        //  1180: aload           19
        //  1182: dup            
        //  1183: astore          25
        //  1185: monitorenter   
        //  1186: aload           9
        //  1188: getfield        P1/u.a:Landroid/content/SharedPreferences;
        //  1191: ldc_w           "vc"
        //  1194: iconst_m1      
        //  1195: invokeinterface android/content/SharedPreferences.getInt:(Ljava/lang/String;I)I
        //  1200: istore_1       
        //  1201: aload           25
        //  1203: monitorexit    
        //  1204: aload           9
        //  1206: invokevirtual   P1/u.e:()V
        //  1209: aload           9
        //  1211: getfield        P1/u.d:Ljava/lang/Object;
        //  1214: astore          20
        //  1216: aload           20
        //  1218: dup            
        //  1219: astore          26
        //  1221: monitorenter   
        //  1222: aload           9
        //  1224: getfield        P1/u.a:Landroid/content/SharedPreferences;
        //  1227: ldc_w           "dm"
        //  1230: aconst_null    
        //  1231: invokeinterface android/content/SharedPreferences.getString:(Ljava/lang/String;Ljava/lang/String;)Ljava/lang/String;
        //  1236: astore          19
        //  1238: aload           26
        //  1240: monitorexit    
        //  1241: aload           9
        //  1243: invokevirtual   P1/u.e:()V
        //  1246: aload           9
        //  1248: getfield        P1/u.d:Ljava/lang/Object;
        //  1251: astore          20
        //  1253: aload           20
        //  1255: dup            
        //  1256: astore          26
        //  1258: monitorenter   
        //  1259: aload           9
        //  1261: getfield        P1/u.a:Landroid/content/SharedPreferences;
        //  1264: ldc_w           "aav"
        //  1267: iconst_m1      
        //  1268: invokeinterface android/content/SharedPreferences.getInt:(Ljava/lang/String;I)I
        //  1273: istore_2       
        //  1274: aload           26
        //  1276: monitorexit    
        //  1277: aload           11
        //  1279: invokevirtual   android/content/Context.getApplicationInfo:()Landroid/content/pm/ApplicationInfo;
        //  1282: getfield        android/content/pm/ApplicationInfo.packageName:Ljava/lang/String;
        //  1285: aload           10
        //  1287: invokestatic    android/text/TextUtils.equals:(Ljava/lang/CharSequence;Ljava/lang/CharSequence;)Z
        //  1290: ifeq            1323
        //  1293: iload_1        
        //  1294: aload           17
        //  1296: getfield        P1/j.e:Landroid/content/pm/PackageInfo;
        //  1299: getfield        android/content/pm/PackageInfo.versionCode:I
        //  1302: if_icmpne       1323
        //  1305: getstatic       android/os/Build.MODEL:Ljava/lang/String;
        //  1308: aload           19
        //  1310: invokestatic    android/text/TextUtils.equals:(Ljava/lang/CharSequence;Ljava/lang/CharSequence;)Z
        //  1313: ifeq            1323
        //  1316: iload_2        
        //  1317: getstatic       android/os/Build$VERSION.SDK_INT:I
        //  1320: if_icmpeq       1326
        //  1323: goto            1663
        //  1326: aload           17
        //  1328: getfield        P1/j.b:LP1/u;
        //  1331: invokevirtual   P1/u.b:()Ljava/util/HashMap;
        //  1334: invokevirtual   java/util/HashMap.entrySet:()Ljava/util/Set;
        //  1337: invokeinterface java/util/Set.iterator:()Ljava/util/Iterator;
        //  1342: astore          9
        //  1344: aload           9
        //  1346: invokeinterface java/util/Iterator.hasNext:()Z
        //  1351: ifeq            1656
        //  1354: aload           9
        //  1356: invokeinterface java/util/Iterator.next:()Ljava/lang/Object;
        //  1361: checkcast       Ljava/util/Map$Entry;
        //  1364: astore          10
        //  1366: new             Lorg/json/JSONObject;
        //  1369: astore          11
        //  1371: aload           11
        //  1373: aload           10
        //  1375: invokeinterface java/util/Map$Entry.getValue:()Ljava/lang/Object;
        //  1380: checkcast       Ljava/lang/String;
        //  1383: invokespecial   org/json/JSONObject.<init>:(Ljava/lang/String;)V
        //  1386: aload           11
        //  1388: ldc_w           "ts_ms"
        //  1391: invokevirtual   org/json/JSONObject.getLong:(Ljava/lang/String;)J
        //  1394: lstore_3       
        //  1395: getstatic       E1/o.B:LE1/o;
        //  1398: astore          11
        //  1400: aload           11
        //  1402: getfield        E1/o.j:Lq2/a;
        //  1405: invokevirtual   java/lang/Object.getClass:()Ljava/lang/Class;
        //  1408: pop            
        //  1409: invokestatic    java/lang/System.currentTimeMillis:()J
        //  1412: lstore          5
        //  1414: getstatic       com/google/android/gms/internal/ads/D7.p7:Lcom/google/android/gms/internal/ads/z7;
        //  1417: astore          20
        //  1419: getstatic       F1/q.d:LF1/q;
        //  1422: astore          19
        //  1424: lload           5
        //  1426: lload_3        
        //  1427: lsub           
        //  1428: aload           19
        //  1430: getfield        F1/q.c:Lcom/google/android/gms/internal/ads/B7;
        //  1433: aload           20
        //  1435: invokevirtual   com/google/android/gms/internal/ads/B7.a:(Lcom/google/android/gms/internal/ads/z7;)Ljava/lang/Object;
        //  1438: checkcast       Ljava/lang/Long;
        //  1441: invokevirtual   java/lang/Long.longValue:()J
        //  1444: lcmp           
        //  1445: ifle            1451
        //  1448: goto            1621
        //  1451: aload           17
        //  1453: getfield        P1/j.a:Landroid/content/Context;
        //  1456: invokestatic    com/google/android/gms/internal/ads/Bs.f:(Landroid/content/Context;)Lcom/google/android/gms/internal/ads/Bs;
        //  1459: astore          20
        //  1461: getstatic       com/google/android/gms/internal/ads/D7.l3:Lcom/google/android/gms/internal/ads/z7;
        //  1464: astore          21
        //  1466: aload           19
        //  1468: getfield        F1/q.c:Lcom/google/android/gms/internal/ads/B7;
        //  1471: aload           21
        //  1473: invokevirtual   com/google/android/gms/internal/ads/B7.a:(Lcom/google/android/gms/internal/ads/z7;)Ljava/lang/Object;
        //  1476: checkcast       Ljava/lang/Long;
        //  1479: invokevirtual   java/lang/Long.longValue:()J
        //  1482: lstore          5
        //  1484: aload           11
        //  1486: getfield        E1/o.g:Lcom/google/android/gms/internal/ads/kd;
        //  1489: invokevirtual   com/google/android/gms/internal/ads/kd.d:()LI1/J;
        //  1492: invokevirtual   I1/J.k:()Z
        //  1495: istore          7
        //  1497: aload           20
        //  1499: invokevirtual   java/lang/Object.getClass:()Ljava/lang/Class;
        //  1502: pop            
        //  1503: ldc_w           Lcom/google/android/gms/internal/ads/Bs;.class
        //  1506: dup            
        //  1507: astore          27
        //  1509: monitorenter   
        //  1510: aload           20
        //  1512: aconst_null    
        //  1513: aconst_null    
        //  1514: lload           5
        //  1516: iload           7
        //  1518: invokevirtual   com/google/android/gms/internal/ads/As.a:(Ljava/lang/String;Ljava/lang/String;JZ)LE1/d;
        //  1521: astore          20
        //  1523: aload           27
        //  1525: monitorexit    
        //  1526: aload           17
        //  1528: getfield        P1/j.a:Landroid/content/Context;
        //  1531: invokestatic    com/google/android/gms/internal/ads/Cs.g:(Landroid/content/Context;)Lcom/google/android/gms/internal/ads/Cs;
        //  1534: astore          21
        //  1536: getstatic       com/google/android/gms/internal/ads/D7.m3:Lcom/google/android/gms/internal/ads/z7;
        //  1539: astore          22
        //  1541: aload           21
        //  1543: aload           19
        //  1545: getfield        F1/q.c:Lcom/google/android/gms/internal/ads/B7;
        //  1548: aload           22
        //  1550: invokevirtual   com/google/android/gms/internal/ads/B7.a:(Lcom/google/android/gms/internal/ads/z7;)Ljava/lang/Object;
        //  1553: checkcast       Ljava/lang/Long;
        //  1556: invokevirtual   java/lang/Long.longValue:()J
        //  1559: aload           11
        //  1561: getfield        E1/o.g:Lcom/google/android/gms/internal/ads/kd;
        //  1564: invokevirtual   com/google/android/gms/internal/ads/kd.d:()LI1/J;
        //  1567: invokevirtual   I1/J.k:()Z
        //  1570: invokevirtual   com/google/android/gms/internal/ads/Cs.f:(JZ)LE1/d;
        //  1573: astore          11
        //  1575: aload           20
        //  1577: getfield        E1/d.D:J
        //  1580: lstore          5
        //  1582: lload           5
        //  1584: ldc2_w          -1
        //  1587: lcmp           
        //  1588: ifeq            1598
        //  1591: lload           5
        //  1593: lload_3        
        //  1594: lcmp           
        //  1595: ifgt            1621
        //  1598: aload           11
        //  1600: getfield        E1/d.D:J
        //  1603: lstore          5
        //  1605: lload           5
        //  1607: ldc2_w          -1
        //  1610: lcmp           
        //  1611: ifeq            1640
        //  1614: lload           5
        //  1616: lload_3        
        //  1617: lcmp           
        //  1618: ifle            1640
        //  1621: aload           17
        //  1623: getfield        P1/j.b:LP1/u;
        //  1626: aload           10
        //  1628: invokeinterface java/util/Map$Entry.getKey:()Ljava/lang/Object;
        //  1633: checkcast       Ljava/lang/String;
        //  1636: invokevirtual   P1/u.a:(Ljava/lang/String;)Ljava/lang/String;
        //  1639: pop            
        //  1640: goto            1344
        //  1643: astore          10
        //  1645: aload           27
        //  1647: monitorexit    
        //  1648: aload           10
        //  1650: athrow         
        //  1651: astore          10
        //  1653: goto            1640
        //  1656: aload           8
        //  1658: astore          9
        //  1660: goto            1718
        //  1663: aload           17
        //  1665: getfield        P1/j.b:LP1/u;
        //  1668: invokevirtual   P1/u.c:()V
        //  1671: aload           17
        //  1673: getfield        P1/j.b:LP1/u;
        //  1676: astore          9
        //  1678: aload           17
        //  1680: getfield        P1/j.a:Landroid/content/Context;
        //  1683: invokevirtual   android/content/Context.getApplicationInfo:()Landroid/content/pm/ApplicationInfo;
        //  1686: getfield        android/content/pm/ApplicationInfo.packageName:Ljava/lang/String;
        //  1689: astore          10
        //  1691: aload           17
        //  1693: getfield        P1/j.e:Landroid/content/pm/PackageInfo;
        //  1696: getfield        android/content/pm/PackageInfo.versionCode:I
        //  1699: istore_1       
        //  1700: aload           9
        //  1702: aload           10
        //  1704: getstatic       android/os/Build.MODEL:Ljava/lang/String;
        //  1707: iload_1        
        //  1708: getstatic       android/os/Build$VERSION.SDK_INT:I
        //  1711: invokevirtual   P1/u.d:(Ljava/lang/String;Ljava/lang/String;II)V
        //  1714: aload           8
        //  1716: astore          9
        //  1718: bipush          31
        //  1720: aload           15
        //  1722: invokestatic    P1/j.c:(ILandroid/os/Bundle;)V
        //  1725: getstatic       E1/o.B:LE1/o;
        //  1728: getfield        E1/o.j:Lq2/a;
        //  1731: invokevirtual   java/lang/Object.getClass:()Ljava/lang/Class;
        //  1734: pop            
        //  1735: invokestatic    java/lang/System.currentTimeMillis:()J
        //  1738: lstore          5
        //  1740: aload           17
        //  1742: getfield        P1/j.c:J
        //  1745: lstore_3       
        //  1746: getstatic       com/google/android/gms/internal/ads/D7.m7:Lcom/google/android/gms/internal/ads/z7;
        //  1749: astore          10
        //  1751: getstatic       F1/q.d:LF1/q;
        //  1754: astore          8
        //  1756: lload           5
        //  1758: lload_3        
        //  1759: lsub           
        //  1760: aload           8
        //  1762: getfield        F1/q.c:Lcom/google/android/gms/internal/ads/B7;
        //  1765: aload           10
        //  1767: invokevirtual   com/google/android/gms/internal/ads/B7.a:(Lcom/google/android/gms/internal/ads/z7;)Ljava/lang/Object;
        //  1770: checkcast       Ljava/lang/Long;
        //  1773: invokevirtual   java/lang/Long.longValue:()J
        //  1776: lcmp           
        //  1777: ifle            1792
        //  1780: iconst_2       
        //  1781: aload           15
        //  1783: invokestatic    P1/j.d:(ILandroid/os/Bundle;)V
        //  1786: aconst_null    
        //  1787: astore          8
        //  1789: goto            2349
        //  1792: bipush          32
        //  1794: aload           15
        //  1796: invokestatic    P1/j.c:(ILandroid/os/Bundle;)V
        //  1799: aload           18
        //  1801: getfield        com/google/android/gms/internal/ads/fd.C:Ljava/lang/String;
        //  1804: astore          19
        //  1806: aload           18
        //  1808: getfield        com/google/android/gms/internal/ads/fd.D:Ljava/lang/String;
        //  1811: astore          21
        //  1813: aload           18
        //  1815: getfield        com/google/android/gms/internal/ads/fd.F:LF1/M0;
        //  1818: getfield        F1/M0.P:Landroid/os/Bundle;
        //  1821: invokevirtual   android/os/Bundle.toString:()Ljava/lang/String;
        //  1824: astore          11
        //  1826: aload           18
        //  1828: getfield        com/google/android/gms/internal/ads/fd.F:LF1/M0;
        //  1831: getfield        F1/M0.E:Landroid/os/Bundle;
        //  1834: invokevirtual   android/os/Bundle.toString:()Ljava/lang/String;
        //  1837: astore          20
        //  1839: aload           18
        //  1841: getfield        com/google/android/gms/internal/ads/fd.F:LF1/M0;
        //  1844: astore          23
        //  1846: aload           23
        //  1848: getfield        F1/M0.K:Ljava/lang/String;
        //  1851: astore          22
        //  1853: aload           23
        //  1855: getfield        F1/M0.R:Ljava/lang/String;
        //  1858: astore          10
        //  1860: aload           23
        //  1862: getfield        F1/M0.Q:Ljava/util/List;
        //  1865: invokestatic    java/lang/String.valueOf:(Ljava/lang/Object;)Ljava/lang/String;
        //  1868: astore          23
        //  1870: new             Ljava/lang/StringBuilder;
        //  1873: dup            
        //  1874: invokespecial   java/lang/StringBuilder.<init>:()V
        //  1877: astore          24
        //  1879: aload           24
        //  1881: aload           19
        //  1883: invokevirtual   java/lang/StringBuilder.append:(Ljava/lang/String;)Ljava/lang/StringBuilder;
        //  1886: pop            
        //  1887: aload           24
        //  1889: aload           21
        //  1891: invokevirtual   java/lang/StringBuilder.append:(Ljava/lang/String;)Ljava/lang/StringBuilder;
        //  1894: pop            
        //  1895: aload           24
        //  1897: aload           11
        //  1899: invokevirtual   java/lang/StringBuilder.append:(Ljava/lang/String;)Ljava/lang/StringBuilder;
        //  1902: pop            
        //  1903: aload           24
        //  1905: aload           20
        //  1907: invokevirtual   java/lang/StringBuilder.append:(Ljava/lang/String;)Ljava/lang/StringBuilder;
        //  1910: pop            
        //  1911: aload           24
        //  1913: aload           22
        //  1915: invokevirtual   java/lang/StringBuilder.append:(Ljava/lang/String;)Ljava/lang/StringBuilder;
        //  1918: pop            
        //  1919: aload           24
        //  1921: aload           10
        //  1923: invokevirtual   java/lang/StringBuilder.append:(Ljava/lang/String;)Ljava/lang/StringBuilder;
        //  1926: pop            
        //  1927: aload           24
        //  1929: aload           23
        //  1931: invokevirtual   java/lang/StringBuilder.append:(Ljava/lang/String;)Ljava/lang/StringBuilder;
        //  1934: pop            
        //  1935: aload           24
        //  1937: invokevirtual   java/lang/StringBuilder.toString:()Ljava/lang/String;
        //  1940: ldc_w           "SHA-256"
        //  1943: invokestatic    J1/e.a:(Ljava/lang/String;Ljava/lang/String;)Ljava/lang/String;
        //  1946: astore          19
        //  1948: aload           19
        //  1950: invokestatic    android/text/TextUtils.isEmpty:(Ljava/lang/CharSequence;)Z
        //  1953: ifeq            1965
        //  1956: iconst_3       
        //  1957: aload           15
        //  1959: invokestatic    P1/j.d:(ILandroid/os/Bundle;)V
        //  1962: goto            1786
        //  1965: bipush          33
        //  1967: aload           15
        //  1969: invokestatic    P1/j.c:(ILandroid/os/Bundle;)V
        //  1972: bipush          34
        //  1974: aload           15
        //  1976: invokestatic    P1/j.c:(ILandroid/os/Bundle;)V
        //  1979: aload           17
        //  1981: getfield        P1/j.b:LP1/u;
        //  1984: aload           19
        //  1986: invokevirtual   P1/u.a:(Ljava/lang/String;)Ljava/lang/String;
        //  1989: astore          10
        //  1991: bipush          35
        //  1993: aload           15
        //  1995: invokestatic    P1/j.c:(ILandroid/os/Bundle;)V
        //  1998: aload           17
        //  2000: invokevirtual   P1/j.b:()Z
        //  2003: ifne            2098
        //  2006: new             Lcom/google/android/gms/internal/ads/fd;
        //  2009: dup            
        //  2010: aload           18
        //  2012: getfield        com/google/android/gms/internal/ads/fd.C:Ljava/lang/String;
        //  2015: aload           18
        //  2017: getfield        com/google/android/gms/internal/ads/fd.D:Ljava/lang/String;
        //  2020: aload           18
        //  2022: getfield        com/google/android/gms/internal/ads/fd.E:LF1/P0;
        //  2025: aload           18
        //  2027: getfield        com/google/android/gms/internal/ads/fd.F:LF1/M0;
        //  2030: iconst_2       
        //  2031: aload           19
        //  2033: invokespecial   com/google/android/gms/internal/ads/fd.<init>:(Ljava/lang/String;Ljava/lang/String;LF1/P0;LF1/M0;ILjava/lang/String;)V
        //  2036: astore          18
        //  2038: aload           17
        //  2040: getfield        P1/j.d:Ljava/util/concurrent/ScheduledExecutorService;
        //  2043: astore          11
        //  2045: new             LA1/b;
        //  2048: dup            
        //  2049: aload           17
        //  2051: aload           19
        //  2053: aload           16
        //  2055: aload           18
        //  2057: bipush          8
        //  2059: invokespecial   A1/b.<init>:(Ljava/lang/Object;Ljava/lang/Object;Ljava/lang/Object;Ljava/lang/Object;I)V
        //  2062: astore          16
        //  2064: getstatic       com/google/android/gms/internal/ads/D7.o7:Lcom/google/android/gms/internal/ads/z7;
        //  2067: astore          17
        //  2069: aload           11
        //  2071: aload           16
        //  2073: aload           8
        //  2075: getfield        F1/q.c:Lcom/google/android/gms/internal/ads/B7;
        //  2078: aload           17
        //  2080: invokevirtual   com/google/android/gms/internal/ads/B7.a:(Lcom/google/android/gms/internal/ads/z7;)Ljava/lang/Object;
        //  2083: checkcast       Ljava/lang/Long;
        //  2086: invokevirtual   java/lang/Long.longValue:()J
        //  2089: getstatic       java/util/concurrent/TimeUnit.MILLISECONDS:Ljava/util/concurrent/TimeUnit;
        //  2092: invokeinterface java/util/concurrent/ScheduledExecutorService.schedule:(Ljava/lang/Runnable;JLjava/util/concurrent/TimeUnit;)Ljava/util/concurrent/ScheduledFuture;
        //  2097: pop            
        //  2098: aload           10
        //  2100: invokestatic    android/text/TextUtils.isEmpty:(Ljava/lang/CharSequence;)Z
        //  2103: ifeq            2115
        //  2106: iconst_4       
        //  2107: aload           15
        //  2109: invokestatic    P1/j.d:(ILandroid/os/Bundle;)V
        //  2112: goto            1786
        //  2115: bipush          36
        //  2117: aload           15
        //  2119: invokestatic    P1/j.c:(ILandroid/os/Bundle;)V
        //  2122: new             Lorg/json/JSONObject;
        //  2125: astore          8
        //  2127: aload           8
        //  2129: aload           10
        //  2131: invokespecial   org/json/JSONObject.<init>:(Ljava/lang/String;)V
        //  2134: aload           8
        //  2136: ldc_w           "sr"
        //  2139: invokevirtual   org/json/JSONObject.getString:(Ljava/lang/String;)Ljava/lang/String;
        //  2142: astore          10
        //  2144: aload           10
        //  2146: invokestatic    android/text/TextUtils.isEmpty:(Ljava/lang/CharSequence;)Z
        //  2149: ifeq            2167
        //  2152: bipush          8
        //  2154: aload           15
        //  2156: invokestatic    P1/j.d:(ILandroid/os/Bundle;)V
        //  2159: goto            1786
        //  2162: astore          8
        //  2164: goto            2326
        //  2167: aload           8
        //  2169: ldc_w           "rs"
        //  2172: invokevirtual   org/json/JSONObject.getString:(Ljava/lang/String;)Ljava/lang/String;
        //  2175: astore          8
        //  2177: aload           8
        //  2179: invokestatic    android/text/TextUtils.isEmpty:(Ljava/lang/CharSequence;)Z
        //  2182: ifeq            2195
        //  2185: bipush          9
        //  2187: aload           15
        //  2189: invokestatic    P1/j.d:(ILandroid/os/Bundle;)V
        //  2192: goto            1786
        //  2195: new             Ljava/lang/String;
        //  2198: astore          11
        //  2200: aload           11
        //  2202: aload           8
        //  2204: bipush          10
        //  2206: invokestatic    android/util/Base64.decode:(Ljava/lang/String;I)[B
        //  2209: getstatic       java/nio/charset/StandardCharsets.UTF_8:Ljava/nio/charset/Charset;
        //  2212: invokespecial   java/lang/String.<init>:([BLjava/nio/charset/Charset;)V
        //  2215: aload           11
        //  2217: invokestatic    P1/j.a:(Ljava/lang/String;)Ljava/lang/String;
        //  2220: astore          16
        //  2222: bipush          37
        //  2224: aload           15
        //  2226: invokestatic    P1/j.c:(ILandroid/os/Bundle;)V
        //  2229: new             LP1/p;
        //  2232: astore          8
        //  2234: new             Landroid/util/JsonReader;
        //  2237: astore          17
        //  2239: new             Ljava/io/StringReader;
        //  2242: astore          11
        //  2244: aload           11
        //  2246: aload           10
        //  2248: invokespecial   java/io/StringReader.<init>:(Ljava/lang/String;)V
        //  2251: aload           17
        //  2253: aload           11
        //  2255: invokespecial   android/util/JsonReader.<init>:(Ljava/io/Reader;)V
        //  2258: aload           8
        //  2260: aload           17
        //  2262: aconst_null    
        //  2263: invokespecial   P1/p.<init>:(Landroid/util/JsonReader;Lcom/google/android/gms/internal/ads/ic;)V
        //  2266: aload           8
        //  2268: aload           16
        //  2270: putfield        P1/p.c:Ljava/lang/String;
        //  2273: aload           8
        //  2275: aload           15
        //  2277: putfield        P1/p.e:Landroid/os/Bundle;
        //  2280: aload           15
        //  2282: ldc_w           "sod_h"
        //  2285: iconst_1       
        //  2286: invokevirtual   android/os/BaseBundle.putBoolean:(Ljava/lang/String;Z)V
        //  2289: goto            2349
        //  2292: astore          8
        //  2294: goto            2299
        //  2297: astore          8
        //  2299: bipush          6
        //  2301: aload           15
        //  2303: invokestatic    P1/j.d:(ILandroid/os/Bundle;)V
        //  2306: getstatic       E1/o.B:LE1/o;
        //  2309: getfield        E1/o.g:Lcom/google/android/gms/internal/ads/kd;
        //  2312: ldc_w           "DiskCachingManager.getSignalResponse"
        //  2315: aload           8
        //  2317: invokevirtual   com/google/android/gms/internal/ads/kd.h:(Ljava/lang/String;Ljava/lang/Throwable;)V
        //  2320: aconst_null    
        //  2321: astore          8
        //  2323: goto            2349
        //  2326: iconst_5       
        //  2327: aload           15
        //  2329: invokestatic    P1/j.d:(ILandroid/os/Bundle;)V
        //  2332: getstatic       E1/o.B:LE1/o;
        //  2335: getfield        E1/o.g:Lcom/google/android/gms/internal/ads/kd;
        //  2338: ldc_w           "DiskCachingManager.getSignalResponse"
        //  2341: aload           8
        //  2343: invokevirtual   com/google/android/gms/internal/ads/kd.h:(Ljava/lang/String;Ljava/lang/Throwable;)V
        //  2346: goto            2320
        //  2349: getstatic       E1/o.B:LE1/o;
        //  2352: getfield        E1/o.j:Lq2/a;
        //  2355: aload           15
        //  2357: ldc_w           "read-from-disk-end"
        //  2360: invokestatic    m0/a.n:(Lq2/a;Landroid/os/Bundle;Ljava/lang/String;)V
        //  2363: goto            2406
        //  2366: astore          8
        //  2368: aload           26
        //  2370: monitorexit    
        //  2371: aload           8
        //  2373: athrow         
        //  2374: astore          8
        //  2376: aload           26
        //  2378: monitorexit    
        //  2379: aload           8
        //  2381: athrow         
        //  2382: astore          8
        //  2384: aload           25
        //  2386: monitorexit    
        //  2387: aload           8
        //  2389: athrow         
        //  2390: astore          8
        //  2392: aload           25
        //  2394: monitorexit    
        //  2395: aload           8
        //  2397: athrow         
        //  2398: aload           8
        //  2400: astore          9
        //  2402: aload           10
        //  2404: astore          8
        //  2406: aload           8
        //  2408: ifnull          2459
        //  2411: aload           12
        //  2413: dup            
        //  2414: astore          28
        //  2416: monitorenter   
        //  2417: new             Lcom/google/android/gms/internal/ads/kn;
        //  2420: astore          9
        //  2422: aload           9
        //  2424: aload           8
        //  2426: bipush          19
        //  2428: invokespecial   com/google/android/gms/internal/ads/kn.<init>:(Ljava/lang/Object;I)V
        //  2431: aload           12
        //  2433: aload           9
        //  2435: invokevirtual   com/google/android/gms/internal/ads/FB.m1:(Lcom/google/android/gms/internal/ads/Wh;)V
        //  2438: aload           28
        //  2440: monitorexit    
        //  2441: aload           8
        //  2443: invokestatic    com/google/android/gms/internal/ads/F7.w0:(Ljava/lang/Object;)Lcom/google/android/gms/internal/ads/Fv;
        //  2446: astore          8
        //  2448: goto            2556
        //  2451: astore          8
        //  2453: aload           28
        //  2455: monitorexit    
        //  2456: aload           8
        //  2458: athrow         
        //  2459: getstatic       com/google/android/gms/internal/ads/uq.V:Lcom/google/android/gms/internal/ads/uq;
        //  2462: astore          8
        //  2464: aload           13
        //  2466: aload           14
        //  2468: invokevirtual   com/google/android/gms/internal/ads/Xg.b:()Lcom/google/android/gms/internal/ads/tq;
        //  2471: aload           8
        //  2473: invokevirtual   com/google/android/gms/internal/ads/xq.a:(LV2/q;Ljava/lang/Object;)Lcom/google/android/gms/internal/ads/k6;
        //  2476: aload           9
        //  2478: invokevirtual   com/google/android/gms/internal/ads/k6.n:(Lcom/google/android/gms/internal/ads/sv;)Lcom/google/android/gms/internal/ads/k6;
        //  2481: astore          8
        //  2483: getstatic       com/google/android/gms/internal/ads/D7.r5:Lcom/google/android/gms/internal/ads/z7;
        //  2486: astore          9
        //  2488: aload           8
        //  2490: getstatic       F1/q.d:LF1/q;
        //  2493: getfield        F1/q.c:Lcom/google/android/gms/internal/ads/B7;
        //  2496: aload           9
        //  2498: invokevirtual   com/google/android/gms/internal/ads/B7.a:(Lcom/google/android/gms/internal/ads/z7;)Ljava/lang/Object;
        //  2501: checkcast       Ljava/lang/Integer;
        //  2504: invokevirtual   java/lang/Integer.intValue:()I
        //  2507: i2l            
        //  2508: getstatic       java/util/concurrent/TimeUnit.SECONDS:Ljava/util/concurrent/TimeUnit;
        //  2511: invokevirtual   com/google/android/gms/internal/ads/k6.s:(JLjava/util/concurrent/TimeUnit;)Lcom/google/android/gms/internal/ads/k6;
        //  2514: invokevirtual   com/google/android/gms/internal/ads/k6.a:()Lcom/google/android/gms/internal/ads/tq;
        //  2517: astore          8
        //  2519: new             Lb1/f;
        //  2522: dup            
        //  2523: aload           12
        //  2525: bipush          28
        //  2527: invokespecial   b1/f.<init>:(Ljava/lang/Object;I)V
        //  2530: astore          10
        //  2532: getstatic       com/google/android/gms/internal/ads/rd.a:Lcom/google/android/gms/internal/ads/pd;
        //  2535: astore          9
        //  2537: aload           8
        //  2539: new             Lcom/google/android/gms/internal/ads/Dv;
        //  2542: dup            
        //  2543: aload           8
        //  2545: iconst_0       
        //  2546: aload           10
        //  2548: invokespecial   com/google/android/gms/internal/ads/Dv.<init>:(Ljava/lang/Object;ILjava/lang/Object;)V
        //  2551: aload           9
        //  2553: invokevirtual   com/google/android/gms/internal/ads/tq.a:(Ljava/lang/Runnable;Ljava/util/concurrent/Executor;)V
        //  2556: aload           8
        //  2558: areturn        
        //  2559: astore          10
        //  2561: goto            1653
        //  2564: astore          10
        //  2566: goto            1640
        //    Exceptions:
        //  Try           Handler
        //  Start  End    Start  End    Type                    
        //  -----  -----  -----  -----  ------------------------
        //  1149   1168   2390   2398   Any
        //  1186   1204   2382   2390   Any
        //  1222   1241   2374   2382   Any
        //  1259   1277   2366   2374   Any
        //  1366   1419   1651   1653   Ljava/io/IOException;
        //  1366   1419   1651   1653   Lorg/json/JSONException;
        //  1419   1424   2559   2564   Ljava/io/IOException;
        //  1419   1424   2559   2564   Lorg/json/JSONException;
        //  1424   1448   2564   2569   Ljava/io/IOException;
        //  1424   1448   2564   2569   Lorg/json/JSONException;
        //  1451   1510   2564   2569   Ljava/io/IOException;
        //  1451   1510   2564   2569   Lorg/json/JSONException;
        //  1510   1526   1643   1651   Any
        //  1526   1582   2564   2569   Ljava/io/IOException;
        //  1526   1582   2564   2569   Lorg/json/JSONException;
        //  1598   1605   2564   2569   Ljava/io/IOException;
        //  1598   1605   2564   2569   Lorg/json/JSONException;
        //  1621   1640   2564   2569   Ljava/io/IOException;
        //  1621   1640   2564   2569   Lorg/json/JSONException;
        //  1645   1648   1643   1651   Any
        //  1648   1651   2564   2569   Ljava/io/IOException;
        //  1648   1651   2564   2569   Lorg/json/JSONException;
        //  2122   2159   2162   2167   Lorg/json/JSONException;
        //  2167   2192   2162   2167   Lorg/json/JSONException;
        //  2195   2229   2162   2167   Lorg/json/JSONException;
        //  2229   2258   2297   2299   Ljava/io/IOException;
        //  2258   2289   2292   2297   Ljava/io/IOException;
        //  2368   2371   2366   2374   Any
        //  2376   2379   2374   2382   Any
        //  2384   2387   2382   2390   Any
        //  2392   2395   2390   2398   Any
        //  2417   2438   2451   2459   Any
        //  2453   2456   2451   2459   Any
        // 
        // The error that occurred was:
        // 
        // java.lang.IndexOutOfBoundsException: Index 1065 out of bounds for length 1065
        //     at jdk.internal.util.Preconditions.outOfBounds(Preconditions.java:64)
        //     at jdk.internal.util.Preconditions.outOfBoundsCheckIndex(Preconditions.java:70)
        //     at jdk.internal.util.Preconditions.checkIndex(Preconditions.java:266)
        //     at java.util.Objects.checkIndex(Objects.java:385)
        //     at java.util.ArrayList.get(ArrayList.java:434)
        //     at q5.g.d(r8-map-id-5336d296fbf3284427aba3c9406dc63d81d5d24d9edcf157bc560c004a742559:31)
        //     at q5.g.b(r8-map-id-5336d296fbf3284427aba3c9406dc63d81d5d24d9edcf157bc560c004a742559:2125)
        //     at u5.m.d(r8-map-id-5336d296fbf3284427aba3c9406dc63d81d5d24d9edcf157bc560c004a742559:21)
        //     at u5.i.g(r8-map-id-5336d296fbf3284427aba3c9406dc63d81d5d24d9edcf157bc560c004a742559:23)
        //     at u5.i.f(r8-map-id-5336d296fbf3284427aba3c9406dc63d81d5d24d9edcf157bc560c004a742559:159)
        //     at u5.i.j(r8-map-id-5336d296fbf3284427aba3c9406dc63d81d5d24d9edcf157bc560c004a742559:619)
        //     at u5.i.k(r8-map-id-5336d296fbf3284427aba3c9406dc63d81d5d24d9edcf157bc560c004a742559:13)
        //     at u5.i.i(r8-map-id-5336d296fbf3284427aba3c9406dc63d81d5d24d9edcf157bc560c004a742559:29)
        //     at s5.b.a(r8-map-id-5336d296fbf3284427aba3c9406dc63d81d5d24d9edcf157bc560c004a742559:90)
        //     at com.thesourceofcode.jadec.decompilers.JavaExtractionWorker.decompileWithProcyon(r8-map-id-5336d296fbf3284427aba3c9406dc63d81d5d24d9edcf157bc560c004a742559:367)
        //     at com.thesourceofcode.jadec.decompilers.JavaExtractionWorker.doWork(r8-map-id-5336d296fbf3284427aba3c9406dc63d81d5d24d9edcf157bc560c004a742559:162)
        //     at com.thesourceofcode.jadec.decompilers.BaseDecompiler.withAttempt(r8-map-id-5336d296fbf3284427aba3c9406dc63d81d5d24d9edcf157bc560c004a742559:3)
        //     at z6.a.run(r8-map-id-5336d296fbf3284427aba3c9406dc63d81d5d24d9edcf157bc560c004a742559:31)
        //     at java.util.concurrent.ThreadPoolExecutor.runWorker(ThreadPoolExecutor.java:1156)
        //     at java.util.concurrent.ThreadPoolExecutor$Worker.run(ThreadPoolExecutor.java:651)
        //     at java.lang.Thread.run(Thread.java:1119)
        // 
        throw new IllegalStateException("An error occurred while decompiling this method.");
    }
}
