package z5;

import B5.w;
import w5.f;
import c5.h;
import e5.d;
import java.util.concurrent.atomic.AtomicReferenceFieldUpdater;
import A5.b;

public final class o extends b implements m, c
{
    public static final AtomicReferenceFieldUpdater G;
    public int F;
    private volatile Object _state;
    
    static {
        G = AtomicReferenceFieldUpdater.newUpdater((Class)o.class, (Class)Object.class, "_state");
    }
    
    public o(final Object state) {
        this._state = state;
    }
    
    public final Object a(final Object o, final d d) {
        this.c(o);
        return h.a;
    }
    
    public final Object b() {
        Object value;
        if ((value = o.G.get((Object)this)) == A5.h.a) {
            value = null;
        }
        return value;
    }
    
    public final void c(final Object o) {
        Object a = o;
        if (o == null) {
            a = A5.h.a;
        }
        o o2 = this;
        monitorenter(this);
        Label_0302: {
            int f;
            try {
                final AtomicReferenceFieldUpdater g = o.G;
                if (n5.h.a(g.get((Object)this), a)) {
                    monitorexit(o2);
                    return;
                }
                g.set((Object)this, a);
                f = this.F;
                if ((f & 0x1) == 0x0) {
                    ++f;
                    this.F = f;
                    A5.c[] array = super.C;
                    monitorexit(o2);
                    while (true) {
                        final q[] array2 = (q[])array;
                        if (array2 != null) {
                            for (final q q : array2) {
                                if (q != null) {
                                Label_0113:
                                    while (true) {
                                        final AtomicReferenceFieldUpdater a2 = q.a;
                                        final Object value = a2.get((Object)q);
                                        if (value == null) {
                                            break;
                                        }
                                        final w b = p.b;
                                        if (value == b) {
                                            break;
                                        }
                                        final w a3 = p.a;
                                        if (value == a3) {
                                            while (!a2.compareAndSet((Object)q, value, (Object)b)) {
                                                if (a2.get((Object)q) != value) {
                                                    continue Label_0113;
                                                }
                                            }
                                            break;
                                        }
                                        while (!a2.compareAndSet((Object)q, value, (Object)a3)) {
                                            if (a2.get((Object)q) != value) {
                                                continue Label_0113;
                                            }
                                        }
                                        ((f)value).h(h.a);
                                        break;
                                    }
                                }
                            }
                        }
                        o2 = this;
                        monitorenter(this);
                        int i;
                        try {
                            i = this.F;
                            if (i == f) {
                                this.F = f + 1;
                                monitorexit(o2);
                                return;
                            }
                        }
                        finally {
                            break;
                        }
                        array = super.C;
                        monitorexit(o2);
                        f = i;
                    }
                    monitorexit(o2);
                }
            }
            finally {
                break Label_0302;
            }
            this.F = f + 2;
            monitorexit(o2);
            return;
        }
        monitorexit(o2);
    }
    
    public final Object e(final z5.d p0, final d p1) {
        // 
        // This method could not be decompiled.
        // 
        // Original Bytecode:
        // 
        //     1: instanceof      Lz5/n;
        //     4: ifeq            38
        //     7: aload_2        
        //     8: checkcast       Lz5/n;
        //    11: astore          7
        //    13: aload           7
        //    15: getfield        z5/n.M:I
        //    18: istore_3       
        //    19: iload_3        
        //    20: ldc             -2147483648
        //    22: iand           
        //    23: ifeq            38
        //    26: aload           7
        //    28: iload_3        
        //    29: ldc             -2147483648
        //    31: iadd           
        //    32: putfield        z5/n.M:I
        //    35: goto            49
        //    38: new             Lz5/n;
        //    41: dup            
        //    42: aload_0        
        //    43: aload_2        
        //    44: invokespecial   z5/n.<init>:(Lz5/o;Le5/d;)V
        //    47: astore          7
        //    49: aload           7
        //    51: getfield        z5/n.K:Ljava/lang/Object;
        //    54: astore          11
        //    56: getstatic       f5/a.C:Lf5/a;
        //    59: astore          20
        //    61: aload           7
        //    63: getfield        z5/n.M:I
        //    66: istore          5
        //    68: iconst_1       
        //    69: istore_3       
        //    70: iconst_1       
        //    71: istore          4
        //    73: iload           5
        //    75: ifeq            260
        //    78: iload           5
        //    80: iconst_1       
        //    81: if_icmpeq       225
        //    84: iload           5
        //    86: iconst_2       
        //    87: if_icmpeq       168
        //    90: iload           5
        //    92: iconst_3       
        //    93: if_icmpne       158
        //    96: aload           7
        //    98: getfield        z5/n.J:Ljava/lang/Object;
        //   101: astore          17
        //   103: aload           7
        //   105: getfield        z5/n.I:Lw5/Q;
        //   108: astore          13
        //   110: aload           7
        //   112: getfield        z5/n.H:Lz5/q;
        //   115: astore          9
        //   117: aload           7
        //   119: getfield        z5/n.G:Lz5/d;
        //   122: astore          12
        //   124: aload           7
        //   126: getfield        z5/n.F:Lz5/o;
        //   129: astore          8
        //   131: aload           9
        //   133: astore_2       
        //   134: aload           8
        //   136: astore_1       
        //   137: aload           11
        //   139: invokestatic    com/google/android/gms/internal/auth/h.z:(Ljava/lang/Object;)V
        //   142: aload           7
        //   144: astore          11
        //   146: aload           8
        //   148: astore          7
        //   150: goto            1132
        //   153: astore          7
        //   155: goto            1148
        //   158: new             Ljava/lang/IllegalStateException;
        //   161: dup            
        //   162: ldc             "call to 'resume' before 'invoke' with coroutine"
        //   164: invokespecial   java/lang/IllegalStateException.<init>:(Ljava/lang/String;)V
        //   167: athrow         
        //   168: aload           7
        //   170: getfield        z5/n.J:Ljava/lang/Object;
        //   173: astore          10
        //   175: aload           7
        //   177: getfield        z5/n.I:Lw5/Q;
        //   180: astore          13
        //   182: aload           7
        //   184: getfield        z5/n.H:Lz5/q;
        //   187: astore          9
        //   189: aload           7
        //   191: getfield        z5/n.G:Lz5/d;
        //   194: astore          14
        //   196: aload           7
        //   198: getfield        z5/n.F:Lz5/o;
        //   201: astore          8
        //   203: aload           9
        //   205: astore_2       
        //   206: aload           8
        //   208: astore_1       
        //   209: aload           11
        //   211: invokestatic    com/google/android/gms/internal/auth/h.z:(Ljava/lang/Object;)V
        //   214: aload           7
        //   216: astore          16
        //   218: aload           10
        //   220: astore          7
        //   222: goto            758
        //   225: aload           7
        //   227: getfield        z5/n.H:Lz5/q;
        //   230: astore          9
        //   232: aload           7
        //   234: getfield        z5/n.G:Lz5/d;
        //   237: astore          10
        //   239: aload           7
        //   241: getfield        z5/n.F:Lz5/o;
        //   244: astore          8
        //   246: aload           9
        //   248: astore_2       
        //   249: aload           8
        //   251: astore_1       
        //   252: aload           11
        //   254: invokestatic    com/google/android/gms/internal/auth/h.z:(Ljava/lang/Object;)V
        //   257: goto            458
        //   260: aload           11
        //   262: invokestatic    com/google/android/gms/internal/auth/h.z:(Ljava/lang/Object;)V
        //   265: aload_0        
        //   266: dup            
        //   267: astore          21
        //   269: monitorenter   
        //   270: aload_0        
        //   271: getfield        A5/b.C:[LA5/c;
        //   274: astore          8
        //   276: aload           8
        //   278: ifnonnull       298
        //   281: iconst_2       
        //   282: anewarray       Lz5/q;
        //   285: astore_2       
        //   286: aload_0        
        //   287: aload_2        
        //   288: putfield        A5/b.C:[LA5/c;
        //   291: goto            341
        //   294: astore_1       
        //   295: goto            1206
        //   298: aload           8
        //   300: astore_2       
        //   301: aload_0        
        //   302: getfield        A5/b.D:I
        //   305: aload           8
        //   307: arraylength    
        //   308: if_icmplt       341
        //   311: aload           8
        //   313: aload           8
        //   315: arraylength    
        //   316: iconst_2       
        //   317: imul           
        //   318: invokestatic    java/util/Arrays.copyOf:([Ljava/lang/Object;I)[Ljava/lang/Object;
        //   321: astore_2       
        //   322: ldc             "copyOf(this, newSize)"
        //   324: aload_2        
        //   325: invokestatic    n5/h.d:(Ljava/lang/String;Ljava/lang/Object;)V
        //   328: aload_0        
        //   329: aload_2        
        //   330: checkcast       [LA5/c;
        //   333: putfield        A5/b.C:[LA5/c;
        //   336: aload_2        
        //   337: checkcast       [LA5/c;
        //   340: astore_2       
        //   341: aload_0        
        //   342: getfield        A5/b.E:I
        //   345: istore_3       
        //   346: aload_2        
        //   347: iload_3        
        //   348: aaload         
        //   349: astore          9
        //   351: aload           9
        //   353: astore          8
        //   355: aload           9
        //   357: ifnonnull       375
        //   360: new             Lz5/q;
        //   363: astore          8
        //   365: aload           8
        //   367: invokespecial   java/lang/Object.<init>:()V
        //   370: aload_2        
        //   371: iload_3        
        //   372: aload           8
        //   374: aastore        
        //   375: iload_3        
        //   376: iconst_1       
        //   377: iadd           
        //   378: istore          5
        //   380: iload           5
        //   382: istore_3       
        //   383: iload           5
        //   385: aload_2        
        //   386: arraylength    
        //   387: if_icmplt       392
        //   390: iconst_0       
        //   391: istore_3       
        //   392: aload           8
        //   394: checkcast       Lz5/q;
        //   397: astore          10
        //   399: getstatic       z5/q.a:Ljava/util/concurrent/atomic/AtomicReferenceFieldUpdater;
        //   402: astore          9
        //   404: aload           9
        //   406: aload           10
        //   408: invokevirtual   java/util/concurrent/atomic/AtomicReferenceFieldUpdater.get:(Ljava/lang/Object;)Ljava/lang/Object;
        //   411: ifnull          417
        //   414: goto            346
        //   417: aload           9
        //   419: aload           10
        //   421: getstatic       z5/p.a:LB5/w;
        //   424: invokevirtual   java/util/concurrent/atomic/AtomicReferenceFieldUpdater.set:(Ljava/lang/Object;Ljava/lang/Object;)V
        //   427: aload_0        
        //   428: iload_3        
        //   429: putfield        A5/b.E:I
        //   432: aload_0        
        //   433: aload_0        
        //   434: getfield        A5/b.D:I
        //   437: iconst_1       
        //   438: iadd           
        //   439: putfield        A5/b.D:I
        //   442: aload           21
        //   444: monitorexit    
        //   445: aload           8
        //   447: checkcast       Lz5/q;
        //   450: astore          9
        //   452: aload_0        
        //   453: astore          8
        //   455: aload_1        
        //   456: astore          10
        //   458: aload           9
        //   460: astore_2       
        //   461: aload           8
        //   463: astore_1       
        //   464: aload           7
        //   466: getfield        g5/c.D:Le5/i;
        //   469: astore          11
        //   471: aload           9
        //   473: astore_2       
        //   474: aload           8
        //   476: astore_1       
        //   477: aload           11
        //   479: invokestatic    n5/h.b:(Ljava/lang/Object;)V
        //   482: aload           9
        //   484: astore_2       
        //   485: aload           8
        //   487: astore_1       
        //   488: aload           11
        //   490: getstatic       w5/t.D:Lw5/t;
        //   493: invokeinterface e5/i.i:(Le5/h;)Le5/g;
        //   498: checkcast       Lw5/Q;
        //   501: astore          13
        //   503: aconst_null    
        //   504: astore          18
        //   506: aload           10
        //   508: astore          12
        //   510: iload           4
        //   512: istore_3       
        //   513: aload           7
        //   515: astore          11
        //   517: aload           9
        //   519: astore_2       
        //   520: aload           8
        //   522: astore_1       
        //   523: getstatic       z5/o.G:Ljava/util/concurrent/atomic/AtomicReferenceFieldUpdater;
        //   526: aload           8
        //   528: invokevirtual   java/util/concurrent/atomic/AtomicReferenceFieldUpdater.get:(Ljava/lang/Object;)Ljava/lang/Object;
        //   531: astore          19
        //   533: aload           13
        //   535: ifnull          572
        //   538: aload           9
        //   540: astore_2       
        //   541: aload           8
        //   543: astore_1       
        //   544: aload           13
        //   546: invokeinterface w5/Q.a:()Z
        //   551: ifeq            557
        //   554: goto            572
        //   557: aload           9
        //   559: astore_2       
        //   560: aload           8
        //   562: astore_1       
        //   563: aload           13
        //   565: checkcast       Lw5/a0;
        //   568: invokevirtual   w5/a0.y:()Ljava/util/concurrent/CancellationException;
        //   571: athrow         
        //   572: aload           18
        //   574: ifnull          620
        //   577: aload           9
        //   579: astore_2       
        //   580: aload           8
        //   582: astore_1       
        //   583: aload           18
        //   585: astore          17
        //   587: aload           11
        //   589: astore          16
        //   591: iload_3        
        //   592: istore          4
        //   594: aload           13
        //   596: astore          15
        //   598: aload           9
        //   600: astore          10
        //   602: aload           12
        //   604: astore          14
        //   606: aload           8
        //   608: astore          7
        //   610: aload           18
        //   612: aload           19
        //   614: invokevirtual   java/lang/Object.equals:(Ljava/lang/Object;)Z
        //   617: ifne            777
        //   620: aload           9
        //   622: astore_2       
        //   623: aload           8
        //   625: astore_1       
        //   626: aload           19
        //   628: getstatic       A5/h.a:LB5/w;
        //   631: if_acmpne       640
        //   634: aconst_null    
        //   635: astore          10
        //   637: goto            644
        //   640: aload           19
        //   642: astore          10
        //   644: aload           9
        //   646: astore_2       
        //   647: aload           8
        //   649: astore_1       
        //   650: aload           11
        //   652: aload           8
        //   654: putfield        z5/n.F:Lz5/o;
        //   657: aload           9
        //   659: astore_2       
        //   660: aload           8
        //   662: astore_1       
        //   663: aload           11
        //   665: aload           12
        //   667: putfield        z5/n.G:Lz5/d;
        //   670: aload           9
        //   672: astore_2       
        //   673: aload           8
        //   675: astore_1       
        //   676: aload           11
        //   678: aload           9
        //   680: putfield        z5/n.H:Lz5/q;
        //   683: aload           9
        //   685: astore_2       
        //   686: aload           8
        //   688: astore_1       
        //   689: aload           11
        //   691: aload           13
        //   693: putfield        z5/n.I:Lw5/Q;
        //   696: aload           9
        //   698: astore_2       
        //   699: aload           8
        //   701: astore_1       
        //   702: aload           11
        //   704: aload           19
        //   706: putfield        z5/n.J:Ljava/lang/Object;
        //   709: aload           9
        //   711: astore_2       
        //   712: aload           8
        //   714: astore_1       
        //   715: aload           11
        //   717: iconst_2       
        //   718: putfield        z5/n.M:I
        //   721: aload           9
        //   723: astore_2       
        //   724: aload           8
        //   726: astore_1       
        //   727: aload           11
        //   729: astore          16
        //   731: aload           19
        //   733: astore          7
        //   735: aload           12
        //   737: astore          14
        //   739: aload           12
        //   741: aload           10
        //   743: aload           11
        //   745: invokeinterface z5/d.a:(Ljava/lang/Object;Le5/d;)Ljava/lang/Object;
        //   750: aload           20
        //   752: if_acmpne       758
        //   755: aload           20
        //   757: areturn        
        //   758: aload           7
        //   760: astore          17
        //   762: aload           8
        //   764: astore          7
        //   766: aload           9
        //   768: astore          10
        //   770: aload           13
        //   772: astore          15
        //   774: iload_3        
        //   775: istore          4
        //   777: aload           10
        //   779: astore_2       
        //   780: aload           7
        //   782: astore_1       
        //   783: aload           10
        //   785: invokevirtual   java/lang/Object.getClass:()Ljava/lang/Class;
        //   788: pop            
        //   789: aload           10
        //   791: astore_2       
        //   792: aload           7
        //   794: astore_1       
        //   795: getstatic       z5/p.a:LB5/w;
        //   798: astore          9
        //   800: aload           10
        //   802: astore_2       
        //   803: aload           7
        //   805: astore_1       
        //   806: getstatic       z5/q.a:Ljava/util/concurrent/atomic/AtomicReferenceFieldUpdater;
        //   809: aload           10
        //   811: aload           9
        //   813: invokevirtual   java/util/concurrent/atomic/AtomicReferenceFieldUpdater.getAndSet:(Ljava/lang/Object;Ljava/lang/Object;)Ljava/lang/Object;
        //   816: astore          8
        //   818: aload           10
        //   820: astore_2       
        //   821: aload           7
        //   823: astore_1       
        //   824: aload           8
        //   826: invokestatic    n5/h.b:(Ljava/lang/Object;)V
        //   829: aload           10
        //   831: astore_2       
        //   832: aload           7
        //   834: astore_1       
        //   835: aload           8
        //   837: getstatic       z5/p.b:LB5/w;
        //   840: if_acmpne       873
        //   843: aload           17
        //   845: astore          18
        //   847: aload           16
        //   849: astore          11
        //   851: iload           4
        //   853: istore_3       
        //   854: aload           15
        //   856: astore          13
        //   858: aload           10
        //   860: astore          9
        //   862: aload           14
        //   864: astore          12
        //   866: aload           7
        //   868: astore          8
        //   870: goto            517
        //   873: aload           10
        //   875: astore_2       
        //   876: aload           7
        //   878: astore_1       
        //   879: aload           16
        //   881: aload           7
        //   883: putfield        z5/n.F:Lz5/o;
        //   886: aload           10
        //   888: astore_2       
        //   889: aload           7
        //   891: astore_1       
        //   892: aload           16
        //   894: aload           14
        //   896: putfield        z5/n.G:Lz5/d;
        //   899: aload           10
        //   901: astore_2       
        //   902: aload           7
        //   904: astore_1       
        //   905: aload           16
        //   907: aload           10
        //   909: putfield        z5/n.H:Lz5/q;
        //   912: aload           10
        //   914: astore_2       
        //   915: aload           7
        //   917: astore_1       
        //   918: aload           16
        //   920: aload           15
        //   922: putfield        z5/n.I:Lw5/Q;
        //   925: aload           10
        //   927: astore_2       
        //   928: aload           7
        //   930: astore_1       
        //   931: aload           16
        //   933: aload           17
        //   935: putfield        z5/n.J:Ljava/lang/Object;
        //   938: aload           10
        //   940: astore_2       
        //   941: aload           7
        //   943: astore_1       
        //   944: aload           16
        //   946: iconst_3       
        //   947: putfield        z5/n.M:I
        //   950: aload           10
        //   952: astore_2       
        //   953: aload           7
        //   955: astore_1       
        //   956: new             Lw5/f;
        //   959: astore          11
        //   961: aload           10
        //   963: astore_2       
        //   964: aload           7
        //   966: astore_1       
        //   967: aload           11
        //   969: iload           4
        //   971: aload           16
        //   973: invokestatic    n3/u0.o:(Le5/d;)Le5/d;
        //   976: invokespecial   w5/f.<init>:(ILe5/d;)V
        //   979: aload           10
        //   981: astore_2       
        //   982: aload           7
        //   984: astore_1       
        //   985: aload           11
        //   987: invokevirtual   w5/f.u:()V
        //   990: aload           10
        //   992: astore_2       
        //   993: aload           7
        //   995: astore_1       
        //   996: getstatic       z5/q.a:Ljava/util/concurrent/atomic/AtomicReferenceFieldUpdater;
        //   999: astore          12
        //  1001: aload           10
        //  1003: astore_2       
        //  1004: aload           7
        //  1006: astore_1       
        //  1007: aload           12
        //  1009: aload           10
        //  1011: aload           9
        //  1013: aload           11
        //  1015: invokevirtual   java/util/concurrent/atomic/AtomicReferenceFieldUpdater.compareAndSet:(Ljava/lang/Object;Ljava/lang/Object;Ljava/lang/Object;)Z
        //  1018: istore          6
        //  1020: aload           10
        //  1022: astore_2       
        //  1023: aload           7
        //  1025: astore_1       
        //  1026: getstatic       c5/h.a:Lc5/h;
        //  1029: astore          8
        //  1031: iload           6
        //  1033: ifeq            1039
        //  1036: goto            1070
        //  1039: aload           10
        //  1041: astore_2       
        //  1042: aload           7
        //  1044: astore_1       
        //  1045: aload           12
        //  1047: aload           10
        //  1049: invokevirtual   java/util/concurrent/atomic/AtomicReferenceFieldUpdater.get:(Ljava/lang/Object;)Ljava/lang/Object;
        //  1052: aload           9
        //  1054: if_acmpeq       1145
        //  1057: aload           10
        //  1059: astore_2       
        //  1060: aload           7
        //  1062: astore_1       
        //  1063: aload           11
        //  1065: aload           8
        //  1067: invokevirtual   w5/f.h:(Ljava/lang/Object;)V
        //  1070: aload           10
        //  1072: astore_2       
        //  1073: aload           7
        //  1075: astore_1       
        //  1076: aload           11
        //  1078: invokevirtual   w5/f.t:()Ljava/lang/Object;
        //  1081: astore          9
        //  1083: aload           10
        //  1085: astore_2       
        //  1086: aload           7
        //  1088: astore_1       
        //  1089: getstatic       f5/a.C:Lf5/a;
        //  1092: astore          11
        //  1094: aload           8
        //  1096: astore_1       
        //  1097: aload           9
        //  1099: aload           11
        //  1101: if_acmpne       1107
        //  1104: aload           9
        //  1106: astore_1       
        //  1107: aload           16
        //  1109: astore          11
        //  1111: aload           15
        //  1113: astore          13
        //  1115: aload           10
        //  1117: astore          9
        //  1119: aload           14
        //  1121: astore          12
        //  1123: aload_1        
        //  1124: aload           20
        //  1126: if_acmpne       1132
        //  1129: aload           20
        //  1131: areturn        
        //  1132: iconst_1       
        //  1133: istore_3       
        //  1134: aload           17
        //  1136: astore          18
        //  1138: aload           7
        //  1140: astore          8
        //  1142: goto            517
        //  1145: goto            990
        //  1148: aload_1        
        //  1149: dup            
        //  1150: astore          22
        //  1152: monitorenter   
        //  1153: aload_1        
        //  1154: getfield        A5/b.D:I
        //  1157: iconst_1       
        //  1158: isub           
        //  1159: istore_3       
        //  1160: aload_1        
        //  1161: iload_3        
        //  1162: putfield        A5/b.D:I
        //  1165: iload_3        
        //  1166: ifne            1181
        //  1169: aload_1        
        //  1170: iconst_0       
        //  1171: putfield        A5/b.E:I
        //  1174: goto            1181
        //  1177: astore_2       
        //  1178: goto            1201
        //  1181: ldc             "null cannot be cast to non-null type kotlinx.coroutines.flow.internal.AbstractSharedFlowSlot<kotlin.Any>"
        //  1183: aload_2        
        //  1184: invokestatic    n5/h.c:(Ljava/lang/String;Ljava/lang/Object;)V
        //  1187: getstatic       z5/q.a:Ljava/util/concurrent/atomic/AtomicReferenceFieldUpdater;
        //  1190: aload_2        
        //  1191: aconst_null    
        //  1192: invokevirtual   java/util/concurrent/atomic/AtomicReferenceFieldUpdater.set:(Ljava/lang/Object;Ljava/lang/Object;)V
        //  1195: aload           22
        //  1197: monitorexit    
        //  1198: aload           7
        //  1200: athrow         
        //  1201: aload           22
        //  1203: monitorexit    
        //  1204: aload_2        
        //  1205: athrow         
        //  1206: aload           21
        //  1208: monitorexit    
        //  1209: aload_1        
        //  1210: athrow         
        //    Exceptions:
        //  Try           Handler
        //  Start  End    Start  End    Type
        //  -----  -----  -----  -----  ----
        //  137    142    153    1206   Any
        //  209    214    153    1206   Any
        //  252    257    153    1206   Any
        //  270    276    294    298    Any
        //  281    291    294    298    Any
        //  301    341    294    298    Any
        //  341    346    294    298    Any
        //  360    370    294    298    Any
        //  383    390    294    298    Any
        //  392    414    294    298    Any
        //  417    442    294    298    Any
        //  464    471    153    1206   Any
        //  477    482    153    1206   Any
        //  488    503    153    1206   Any
        //  523    533    153    1206   Any
        //  544    554    153    1206   Any
        //  563    572    153    1206   Any
        //  610    620    153    1206   Any
        //  626    634    153    1206   Any
        //  650    657    153    1206   Any
        //  663    670    153    1206   Any
        //  676    683    153    1206   Any
        //  689    696    153    1206   Any
        //  702    709    153    1206   Any
        //  715    721    153    1206   Any
        //  739    755    153    1206   Any
        //  783    789    153    1206   Any
        //  795    800    153    1206   Any
        //  806    818    153    1206   Any
        //  824    829    153    1206   Any
        //  835    843    153    1206   Any
        //  879    886    153    1206   Any
        //  892    899    153    1206   Any
        //  905    912    153    1206   Any
        //  918    925    153    1206   Any
        //  931    938    153    1206   Any
        //  944    950    153    1206   Any
        //  956    961    153    1206   Any
        //  967    979    153    1206   Any
        //  985    990    153    1206   Any
        //  996    1001   153    1206   Any
        //  1007   1020   153    1206   Any
        //  1026   1031   153    1206   Any
        //  1045   1057   153    1206   Any
        //  1063   1070   153    1206   Any
        //  1076   1083   153    1206   Any
        //  1089   1094   153    1206   Any
        //  1153   1165   1177   1181   Any
        //  1169   1174   1177   1181   Any
        //  1181   1195   1177   1181   Any
        // 
        // The error that occurred was:
        // 
        // java.lang.NullPointerException: Attempt to invoke virtual method 'g5.m0 g5.d2.L()' on a null object reference
        //     at e5.d0.e(r8-map-id-5336d296fbf3284427aba3c9406dc63d81d5d24d9edcf157bc560c004a742559:26)
        //     at e5.c0.s(r8-map-id-5336d296fbf3284427aba3c9406dc63d81d5d24d9edcf157bc560c004a742559:1643)
        //     at q5.g.o(r8-map-id-5336d296fbf3284427aba3c9406dc63d81d5d24d9edcf157bc560c004a742559:2651)
        //     at q5.g.b(r8-map-id-5336d296fbf3284427aba3c9406dc63d81d5d24d9edcf157bc560c004a742559:2099)
        //     at u5.m.d(r8-map-id-5336d296fbf3284427aba3c9406dc63d81d5d24d9edcf157bc560c004a742559:21)
        //     at u5.i.g(r8-map-id-5336d296fbf3284427aba3c9406dc63d81d5d24d9edcf157bc560c004a742559:23)
        //     at u5.i.f(r8-map-id-5336d296fbf3284427aba3c9406dc63d81d5d24d9edcf157bc560c004a742559:159)
        //     at u5.i.j(r8-map-id-5336d296fbf3284427aba3c9406dc63d81d5d24d9edcf157bc560c004a742559:619)
        //     at u5.i.k(r8-map-id-5336d296fbf3284427aba3c9406dc63d81d5d24d9edcf157bc560c004a742559:13)
        //     at u5.i.i(r8-map-id-5336d296fbf3284427aba3c9406dc63d81d5d24d9edcf157bc560c004a742559:29)
        //     at s5.b.a(r8-map-id-5336d296fbf3284427aba3c9406dc63d81d5d24d9edcf157bc560c004a742559:90)
        //     at com.thesourceofcode.jadec.decompilers.JavaExtractionWorker.decompileWithProcyon(r8-map-id-5336d296fbf3284427aba3c9406dc63d81d5d24d9edcf157bc560c004a742559:367)
        //     at com.thesourceofcode.jadec.decompilers.JavaExtractionWorker.doWork(r8-map-id-5336d296fbf3284427aba3c9406dc63d81d5d24d9edcf157bc560c004a742559:162)
        //     at com.thesourceofcode.jadec.decompilers.BaseDecompiler.withAttempt(r8-map-id-5336d296fbf3284427aba3c9406dc63d81d5d24d9edcf157bc560c004a742559:3)
        //     at z6.a.run(r8-map-id-5336d296fbf3284427aba3c9406dc63d81d5d24d9edcf157bc560c004a742559:31)
        //     at java.util.concurrent.ThreadPoolExecutor.runWorker(ThreadPoolExecutor.java:1156)
        //     at java.util.concurrent.ThreadPoolExecutor$Worker.run(ThreadPoolExecutor.java:651)
        //     at java.lang.Thread.run(Thread.java:1119)
        // 
        throw new IllegalStateException("An error occurred while decompiling this method.");
    }
}
